Workbook

Sheet Résumé
A1: Tableau de bord du catalogue
A3: =+A22 -> Formations PUI
A4: Catalogue de ressources de l'innovation et l'entrepreneuriat | B4: Date mise à jour | C4: 46294
A5: Formations PUI (fondateurs) | C5: 87
A6: Formations externes | C6: 21
A7: Formateurs par thématiques | C7: 34
A8: Lieux de l'innovation | C8: 21
A9: Equipements | C9: 18
A10: Outils innovation | C10: 62
A11: Bibliographie | C11: 32
A12: Contact Valo | C12: 1
A13: Financements | C13: 21
A14: Se former pour l'avenir | C14: 6
A16: Phase collecte V2 | C16: 1
A21: Définitions
A22: Formations PUI | B22: Formations qui sont dispensées dans au moins un établissement de l'Université Paris Saclay faisant partie des fondateurs PUI
A23: Formations externes | B23: Formations disponibles dans d'autres plateformes ou établissements en dehors du P14
A24: Formateurs | B24: Personnes ressources clé internes ou externes auxquelles nous pourrions faire appel pour la création de contenus et/ou formations
A25: Lieux de l'innovation | B25: Locaux habilités pour réaliser des activités de formation, entrepreneuriat et innovation
A26: Equipements | B26: Equipements et technologies disponibles pour la formation, prototypage, entrepreneuriat, etc
A27: Outils | B27: Supports et outils pratiques (fiches, plaquettes, jeux, …)
A28: Bibliographie | B28: Livres, articles, revues, textes et contenus web utilisés comme référence lors de la recherche pour la conception de la formation

Sheet Formations PUI
A1: Formations
A2: N | B2: Titre de la formation | C2: Objectifs pédagogiques du dispositif | D2: Etablissement | E2: Niveau | F2: Modalités pédagogiques / méthodologie | G2: Format | H2: Durée | I2: Modalité | J2: Public ciblé | K2: Pays | L2: Langue | M2: Coût | N2: web | O2: Contact | P2: Mail | Q2: Localisation | R2: CONTRIBUTEUR
A3: 1 | B3: Master innovation et valorisation de la recherche | C3: Design and implement future-focused innovation strategies that can be applied to any industry. Learn alongside a global cohort of like-minded professionals | D3: Université Paris-Saclay | E3: Master | F3: Cours magistraux, TP | G3: 2 jours par semaine | H3: 1 an | I3: Présentiel | J3: Bac +4 | K3: France | L3: Français- anglais | M3: 6000 | O3: Nicolas Soulié, Anne Plunket | Q3: Faculté Jean Monnet
A4: 1 | B4: Management de la R&D et de l’innovation | C4: Panorama des connaissances (théories et méthodologies) allant de la stratégie de R&D d’une entreprise à l’ingénierie de développement d’une offre de valeur (produit ou service accompagné de son modèle économique) en passant par la définition de roadmaps marchés et technologies, de plans produits, de la maitrise des coûts de R&D et des projets de développement, ainsi que des processus et problématiques d’innovation (incluant la protection de l’innovation, la gestion des compétences, les stratégies de partenariat et d’innovation ouverte). 1. Découvrir tous les étages de l’entreprise innovante : son écosystème, sa stratégie, sa R&D, sa gestion de l’innovation et ses projets de développement de produits / services / modèles économiques nouveaux. 2. Préparer aux métiers de l’innovation et de l’intraprenariat qui sont des métiers récents en France et en Europe : métiers de directeur innovation, manager-ingénieur de l’innovation durable, aux rôles d’interfaces sur la chaine de la valeur (comme responsable projet innovant, responsable du développement de l’innovation ouverte…). 3. Articuler la stratégie de l’entreprise avec les théories et méthodologies du management de l’innovation, du management des technologies, des ingénieries de développement, conception et lancement de produits. | D4: Centrale Supélec | E4: Cours | F4: Cours magistraux, TP | G4: Le cours est composé de 9 séances thématiques de 3h. Chaque séance inclut un TD d’une durée de 30 minutes à 1h30 | I4: Présentiel | J4: Etudiants | K4: France | L4: Français | O4: Bernard Yannou | P4: bernard.yannou@centralesupelec.fr | Q4: Centrale SupElec | R4: Bernard Yannou
A5: 1 | B5: Radical innovation Design | C5: Cet atelier vise à avoir une utilisation poussée de la méthodologie de gestion de projets d’innovation Radical Innovation Design, dans le cadre du lancement d’une start-up dans le domaine de la silver économie. Radical Innovation Design est une méthodologie de gestion de projets d'innovation, made in CentraleSupélec, qui a fait l'objet d'une start-up, d'un jeu sérieux et d'un eBook en accès gratuit (https://doi.org/10.1051/978-2- 7598-3066-4) qui permet d'accéder à de multiples ressources. La méthodologie en elle-même est qualifiable d'ingénierie de l'innovation, car elle introduit de nouveaux concepts, méthodes, et une plateforme informatisée pour poser un problème d'innovation complexe, cibler les zones d'intérêt qui créent de l'utilité pour les usagers et de la profitabilité pour l'entreprise, et "idéer" une solution système et son modèle économique optimaux. Silver Valley, qui est un regroupement d’acteurs qui fédère près de 300 organisations de la Silver Économie - filière transversale qui répond aux besoins et usages des seniors et de leur entourage -, est partenaire de l’atelier. C’est un écosystème unique en Europe qui a pour objectif de préparer la société de la longévité, d’accélérer le développement et la mise sur le marché de solutions innovantes pour favoriser le mieux-vieillir, l’inclusion des personnes et générer croissance et emploi. Silver Valley a notamment développé le dispositif Open Lab : une communauté de seniors, participant à des séances de co-design, de tests et d’expérimentations des solutions portées par les entrepreneurs. CentraleSupélec a participé au développement de Silver Valley, notamment au développement du dispositif d’innovation Scale Up Lab® qui s’inspire de la méthodologie Radical Innovation design® pour sélectionner et accompagner les start-ups dans leur croissance, expérimentation et réseautage. L’atelier consiste à utiliser et améliorer un processus d’étude rapide et systématique d’un potentiel d’innovation dans le domaine de la Silver Economie, en utilisant Radical Innovation Design, l’IA générative (ChatGPT) et toutes les études disponibles sur les activités et situations d’usage des personnes âgées. L’atelier sera centré sur l’obtention de structurations satisfaisantes des activités des seniors, de cartographies de problèmes ou pain points des activités des seniors, qui à leur tour serviront à orienter les concepteurs de solutions nouvelles et start- upers vers le développement de solutions utiles pour « augmenter » l’activité de ces seniors. | D5: Centrale Supélec | E5: Cours | F5: Cours magistraux, TP | G5: L’atelier se compose de 6 séances de 3h. | J5: Etudiants | K5: France | L5: Français | O5: Bernard Yannou | P5: bernard.yannou@centralesupelec.fr | Q5: Centrale SupElec | R5: Bernard Yannou
A6: 1 | B6: CMA design et transitions | D6: Centrale Supélec | F6: Cours magistraux, TP | I6: Présentiel | J6: Etudiants | K6: France | L6: Français | O6: Bernard Yannou | P6: bernard.yannou@centralesupelec.fr | Q6: Centrale SupElec | R6: Bernard Yannou
A7: 1 | B7: Les Midis de l'entrepreneuriat | C7: Créer sa landing page sans savoir coder en 48 heures | D7: Diogale | F7: Animé par Doudou Diof | G7: 45581 | I7: Distanciel | J7: Etudiants DU | K7: France | L7: Français | N7: https://teams.microsoft.com/dl/launcher/launcher.html?url=%2F_%23%2Fl%2Fmeetup-join%2F19%3Ameeting_NGZiZWIzZjctMWE0Yi00YmI4LTk2ZTctNjA5ZGM3NGMwOTgw%40thread.v2%2F0%3Fcontext%3D%257b%2522Tid%2522%253a%252268cdfebb-157b-4846-ba2f-d196a9124ac0%2522%252c%2522Oid%2522%253a%25222aa70631-91e8-4b12-b01e-79459d41d6b5%2522%257d%26anon%3Dtrue&type=meetup-join&deeplinkId=195361cc-271b-4f88-be91-e82a4d57ad9d&directDl=true&msLaunch=true&enableMobilePage=true&suppressPrompt=true | O7: Carole Poiré | P7: carole.poire@universite-paris-saclay.fr | Q7: Paris Saclay | R7: Sophie Dondeyne
A8: 1 | B8: Les Midis de l'entrepreneuriat | C8: Quelle idée pour créer ton entreprise ? | D8: Innowide | F8: Animé par Damien Cuoq | G8: 45588 | I8: Distanciel | J8: Etudiants DU | K8: France | L8: Français | N8: https://teams.microsoft.com/dl/launcher/launcher.html?url=%2F_%23%2Fl%2Fmeetup-join%2F19%3Ameeting_NGZiZWIzZjctMWE0Yi00YmI4LTk2ZTctNjA5ZGM3NGMwOTgw%40thread.v2%2F0%3Fcontext%3D%257b%2522Tid%2522%253a%252268cdfebb-157b-4846-ba2f-d196a9124ac0%2522%252c%2522Oid%2522%253a%25222aa70631-91e8-4b12-b01e-79459d41d6b5%2522%257d%26anon%3Dtrue&type=meetup-join&deeplinkId=195361cc-271b-4f88-be91-e82a4d57ad9d&directDl=true&msLaunch=true&enableMobilePage=true&suppressPrompt=true | O8: Carole Poiré | P8: carole.poire@universite-paris-saclay.fr | Q8: Paris Saclay | R8: Sophie Dondeyne
A9: 1 | B9: Les Midis de l'entrepreneuriat | C9: De l'idée à l'action : concevoir et lancer votre startup | D9: Start in Saclay | G9: 45602 | I9: Distanciel | J9: Etudiants DU | K9: France | L9: Français | N9: https://teams.microsoft.com/dl/launcher/launcher.html?url=%2F_%23%2Fl%2Fmeetup-join%2F19%3Ameeting_NGZiZWIzZjctMWE0Yi00YmI4LTk2ZTctNjA5ZGM3NGMwOTgw%40thread.v2%2F0%3Fcontext%3D%257b%2522Tid%2522%253a%252268cdfebb-157b-4846-ba2f-d196a9124ac0%2522%252c%2522Oid%2522%253a%25222aa70631-91e8-4b12-b01e-79459d41d6b5%2522%257d%26anon%3Dtrue&type=meetup-join&deeplinkId=195361cc-271b-4f88-be91-e82a4d57ad9d&directDl=true&msLaunch=true&enableMobilePage=true&suppressPrompt=true | O9: Carole Poiré | P9: carole.poire@universite-paris-saclay.fr | Q9: Paris Saclay | R9: Sophie Dondeyne
A10: 1 | B10: Les Midis de l'entrepreneuriat | C10: Les conseils pour avoir un pitch convaincant | D10: Association EGEE | G10: 45609 | I10: Distanciel | J10: Etudiants DU | K10: France | L10: Français | N10: https://teams.microsoft.com/dl/launcher/launcher.html?url=%2F_%23%2Fl%2Fmeetup-join%2F19%3Ameeting_NGZiZWIzZjctMWE0Yi00YmI4LTk2ZTctNjA5ZGM3NGMwOTgw%40thread.v2%2F0%3Fcontext%3D%257b%2522Tid%2522%253a%252268cdfebb-157b-4846-ba2f-d196a9124ac0%2522%252c%2522Oid%2522%253a%25222aa70631-91e8-4b12-b01e-79459d41d6b5%2522%257d%26anon%3Dtrue&type=meetup-join&deeplinkId=195361cc-271b-4f88-be91-e82a4d57ad9d&directDl=true&msLaunch=true&enableMobilePage=true&suppressPrompt=true | O10: Carole Poiré | P10: carole.poire@universite-paris-saclay.fr | Q10: Paris Saclay | R10: Sophie Dondeyne
A11: 1 | B11: Les Midis de l'entrepreneuriat | C11: Les outils à connaitre pour son projet d'entreprise | D11: Design Spot | F11: Annimé par Yoann Montenot | G11: 45616 | I11: Distanciel | J11: Etudiants DU | K11: France | L11: Français | N11: https://teams.microsoft.com/dl/launcher/launcher.html?url=%2F_%23%2Fl%2Fmeetup-join%2F19%3Ameeting_NGZiZWIzZjctMWE0Yi00YmI4LTk2ZTctNjA5ZGM3NGMwOTgw%40thread.v2%2F0%3Fcontext%3D%257b%2522Tid%2522%253a%252268cdfebb-157b-4846-ba2f-d196a9124ac0%2522%252c%2522Oid%2522%253a%25222aa70631-91e8-4b12-b01e-79459d41d6b5%2522%257d%26anon%3Dtrue&type=meetup-join&deeplinkId=195361cc-271b-4f88-be91-e82a4d57ad9d&directDl=true&msLaunch=true&enableMobilePage=true&suppressPrompt=true | O11: Carole Poiré | P11: carole.poire@universite-paris-saclay.fr | Q11: Paris Saclay | R11: Sophie Dondeyne
A12: 1 | B12: Les Midis de l'entrepreneuriat | C12: Le modéle économique | D12: Université Paris-Saclay | G12: 45623 | I12: Distanciel | J12: Etudiants DU | K12: France | L12: Français | N12: https://teams.microsoft.com/dl/launcher/launcher.html?url=%2F_%23%2Fl%2Fmeetup-join%2F19%3Ameeting_NGZiZWIzZjctMWE0Yi00YmI4LTk2ZTctNjA5ZGM3NGMwOTgw%40thread.v2%2F0%3Fcontext%3D%257b%2522Tid%2522%253a%252268cdfebb-157b-4846-ba2f-d196a9124ac0%2522%252c%2522Oid%2522%253a%25222aa70631-91e8-4b12-b01e-79459d41d6b5%2522%257d%26anon%3Dtrue&type=meetup-join&deeplinkId=195361cc-271b-4f88-be91-e82a4d57ad9d&directDl=true&msLaunch=true&enableMobilePage=true&suppressPrompt=true | O12: Carole Poiré | P12: carole.poire@universite-paris-saclay.fr | Q12: Paris Saclay | R12: Sophie Dondeyne
A13: 1 | B13: Les Midis de l'entrepreneuriat | C13: Entreprendre en deeptech : défis et opportunités | D13: Start in Saclay | G13: 45630 | I13: Distanciel | J13: Etudiants DU | K13: France | L13: Français | N13: https://teams.microsoft.com/dl/launcher/launcher.html?url=%2F_%23%2Fl%2Fmeetup-join%2F19%3Ameeting_NGZiZWIzZjctMWE0Yi00YmI4LTk2ZTctNjA5ZGM3NGMwOTgw%40thread.v2%2F0%3Fcontext%3D%257b%2522Tid%2522%253a%252268cdfebb-157b-4846-ba2f-d196a9124ac0%2522%252c%2522Oid%2522%253a%25222aa70631-91e8-4b12-b01e-79459d41d6b5%2522%257d%26anon%3Dtrue&type=meetup-join&deeplinkId=195361cc-271b-4f88-be91-e82a4d57ad9d&directDl=true&msLaunch=true&enableMobilePage=true&suppressPrompt=true | O13: Carole Poiré | P13: carole.poire@universite-paris-saclay.fr | Q13: Paris Saclay | R13: Sophie Dondeyne
A14: 1 | B14: Les Midis de l'entrepreneuriat | C14: Aide à la recherche documentaire pour réaliser une étude de marché | D14: Université Paris-Saclay | F14: Animé par Imelda Lemoing | G14: 45686 | I14: Distanciel | J14: Etudiants DU | K14: France | L14: Français | N14: https://teams.microsoft.com/dl/launcher/launcher.html?url=%2F_%23%2Fl%2Fmeetup-join%2F19%3Ameeting_NGZiZWIzZjctMWE0Yi00YmI4LTk2ZTctNjA5ZGM3NGMwOTgw%40thread.v2%2F0%3Fcontext%3D%257b%2522Tid%2522%253a%252268cdfebb-157b-4846-ba2f-d196a9124ac0%2522%252c%2522Oid%2522%253a%25222aa70631-91e8-4b12-b01e-79459d41d6b5%2522%257d%26anon%3Dtrue&type=meetup-join&deeplinkId=195361cc-271b-4f88-be91-e82a4d57ad9d&directDl=true&msLaunch=true&enableMobilePage=true&suppressPrompt=true | O14: Carole Poiré | P14: carole.poire@universite-paris-saclay.fr | Q14: Paris Saclay | R14: Sophie Dondeyne
A15: 1 | B15: Les Midis de l'entrepreneuriat | C15: Débuter sans argent | D15: Graines de conseil | F15: Animé par Bertrand De Saint Viance | G15: 45693 | I15: Distanciel | J15: Etudiants DU | K15: France | L15: Français | N15: https://teams.microsoft.com/dl/launcher/launcher.html?url=%2F_%23%2Fl%2Fmeetup-join%2F19%3Ameeting_NGZiZWIzZjctMWE0Yi00YmI4LTk2ZTctNjA5ZGM3NGMwOTgw%40thread.v2%2F0%3Fcontext%3D%257b%2522Tid%2522%253a%252268cdfebb-157b-4846-ba2f-d196a9124ac0%2522%252c%2522Oid%2522%253a%25222aa70631-91e8-4b12-b01e-79459d41d6b5%2522%257d%26anon%3Dtrue&type=meetup-join&deeplinkId=195361cc-271b-4f88-be91-e82a4d57ad9d&directDl=true&msLaunch=true&enableMobilePage=true&suppressPrompt=true | O15: Carole Poiré | P15: carole.poire@universite-paris-saclay.fr | Q15: Paris Saclay | R15: Sophie Dondeyne
A16: 1 | B16: Les Midis de l'entrepreneuriat | C16: Les étapes de la création d'entreprise | D16: Vallée Sud Grand Paris | F16: Animé par Farrouk Khenoussi | G16: 45700 | I16: Distanciel | J16: Etudiants DU | K16: France | L16: Français | N16: https://teams.microsoft.com/dl/launcher/launcher.html?url=%2F_%23%2Fl%2Fmeetup-join%2F19%3Ameeting_NGZiZWIzZjctMWE0Yi00YmI4LTk2ZTctNjA5ZGM3NGMwOTgw%40thread.v2%2F0%3Fcontext%3D%257b%2522Tid%2522%253a%252268cdfebb-157b-4846-ba2f-d196a9124ac0%2522%252c%2522Oid%2522%253a%25222aa70631-91e8-4b12-b01e-79459d41d6b5%2522%257d%26anon%3Dtrue&type=meetup-join&deeplinkId=195361cc-271b-4f88-be91-e82a4d57ad9d&directDl=true&msLaunch=true&enableMobilePage=true&suppressPrompt=true | O16: Carole Poiré | P16: carole.poire@universite-paris-saclay.fr | Q16: Paris Saclay | R16: Sophie Dondeyne
A17: 1 | B17: Les Midis de l'entrepreneuriat | C17: Le développement et la construction de sa stratégie sur la propriété intelectuelle | D17: INPI | F17: Animé par Sophie Djega Mariadassou | G17: 45728 | I17: Distanciel | J17: Etudiants DU | K17: France | L17: Français | N17: https://teams.microsoft.com/dl/launcher/launcher.html?url=%2F_%23%2Fl%2Fmeetup-join%2F19%3Ameeting_NGZiZWIzZjctMWE0Yi00YmI4LTk2ZTctNjA5ZGM3NGMwOTgw%40thread.v2%2F0%3Fcontext%3D%257b%2522Tid%2522%253a%252268cdfebb-157b-4846-ba2f-d196a9124ac0%2522%252c%2522Oid%2522%253a%25222aa70631-91e8-4b12-b01e-79459d41d6b5%2522%257d%26anon%3Dtrue&type=meetup-join&deeplinkId=195361cc-271b-4f88-be91-e82a4d57ad9d&directDl=true&msLaunch=true&enableMobilePage=true&suppressPrompt=true | O17: Carole Poiré | P17: carole.poire@universite-paris-saclay.fr | Q17: Paris Saclay | R17: Sophie Dondeyne
A18: 1 | B18: Les Midis de l'entrepreneuriat | C18: Accélérateurs et incubateurs : catalyseurs de réussite | D18: Start in Saclay | G18: 45735 | I18: Distanciel | J18: Etudiants DU | K18: France | L18: Français | N18: https://teams.microsoft.com/dl/launcher/launcher.html?url=%2F_%23%2Fl%2Fmeetup-join%2F19%3Ameeting_NGZiZWIzZjctMWE0Yi00YmI4LTk2ZTctNjA5ZGM3NGMwOTgw%40thread.v2%2F0%3Fcontext%3D%257b%2522Tid%2522%253a%252268cdfebb-157b-4846-ba2f-d196a9124ac0%2522%252c%2522Oid%2522%253a%25222aa70631-91e8-4b12-b01e-79459d41d6b5%2522%257d%26anon%3Dtrue&type=meetup-join&deeplinkId=195361cc-271b-4f88-be91-e82a4d57ad9d&directDl=true&msLaunch=true&enableMobilePage=true&suppressPrompt=true | O18: Carole Poiré | P18: carole.poire@universite-paris-saclay.fr | Q18: Paris Saclay | R18: Sophie Dondeyne
A19: 1 | B19: Les Midis de l'entrepreneuriat | C19: Les stratégies commerciales et les techniques de vente | D19: Association EGEE | F19: Animé par Jacques Bonnement | G19: 45742 | I19: Distanciel | J19: Etudiants DU | K19: France | L19: Français | N19: https://teams.microsoft.com/dl/launcher/launcher.html?url=%2F_%23%2Fl%2Fmeetup-join%2F19%3Ameeting_NGZiZWIzZjctMWE0Yi00YmI4LTk2ZTctNjA5ZGM3NGMwOTgw%40thread.v2%2F0%3Fcontext%3D%257b%2522Tid%2522%253a%252268cdfebb-157b-4846-ba2f-d196a9124ac0%2522%252c%2522Oid%2522%253a%25222aa70631-91e8-4b12-b01e-79459d41d6b5%2522%257d%26anon%3Dtrue&type=meetup-join&deeplinkId=195361cc-271b-4f88-be91-e82a4d57ad9d&directDl=true&msLaunch=true&enableMobilePage=true&suppressPrompt=true | O19: Carole Poiré | P19: carole.poire@universite-paris-saclay.fr | Q19: Paris Saclay | R19: Sophie Dondeyne
A20: 1 | B20: Les Midis de l'entrepreneuriat | C20: Accélérer la croissance : les clés pour réussir sa levée de fonds | D20: Start in Saclay | G20: 45749 | I20: Distanciel | J20: Etudiants DU | K20: France | L20: Français | N20: https://teams.microsoft.com/dl/launcher/launcher.html?url=%2F_%23%2Fl%2Fmeetup-join%2F19%3Ameeting_NGZiZWIzZjctMWE0Yi00YmI4LTk2ZTctNjA5ZGM3NGMwOTgw%40thread.v2%2F0%3Fcontext%3D%257b%2522Tid%2522%253a%252268cdfebb-157b-4846-ba2f-d196a9124ac0%2522%252c%2522Oid%2522%253a%25222aa70631-91e8-4b12-b01e-79459d41d6b5%2522%257d%26anon%3Dtrue&type=meetup-join&deeplinkId=195361cc-271b-4f88-be91-e82a4d57ad9d&directDl=true&msLaunch=true&enableMobilePage=true&suppressPrompt=true | O20: Carole Poiré | P20: carole.poire@universite-paris-saclay.fr | Q20: Paris Saclay | R20: Sophie Dondeyne
A21: 1 | B21: Les Midis de l'entrepreneuriat | C21: Les stratégies marketing | D21: Association EGEE | F21: Animé par Jacques Bonnement | G21: 45756 | I21: Distanciel | J21: Etudiants DU | K21: France | L21: Français | N21: https://teams.microsoft.com/dl/launcher/launcher.html?url=%2F_%23%2Fl%2Fmeetup-join%2F19%3Ameeting_NGZiZWIzZjctMWE0Yi00YmI4LTk2ZTctNjA5ZGM3NGMwOTgw%40thread.v2%2F0%3Fcontext%3D%257b%2522Tid%2522%253a%252268cdfebb-157b-4846-ba2f-d196a9124ac0%2522%252c%2522Oid%2522%253a%25222aa70631-91e8-4b12-b01e-79459d41d6b5%2522%257d%26anon%3Dtrue&type=meetup-join&deeplinkId=195361cc-271b-4f88-be91-e82a4d57ad9d&directDl=true&msLaunch=true&enableMobilePage=true&suppressPrompt=true | O21: Carole Poiré | P21: carole.poire@universite-paris-saclay.fr | Q21: Paris Saclay | R21: Sophie Dondeyne
A22: 1 | B22: Les Midis de l'entrepreneuriat | C22: Startups à impact : entreprendre pour un monde meilleur | D22: Start in Saclay | G22: 45770 | I22: Distanciel | J22: Etudiants DU | K22: France | L22: Français | N22: https://teams.microsoft.com/dl/launcher/launcher.html?url=%2F_%23%2Fl%2Fmeetup-join%2F19%3Ameeting_NGZiZWIzZjctMWE0Yi00YmI4LTk2ZTctNjA5ZGM3NGMwOTgw%40thread.v2%2F0%3Fcontext%3D%257b%2522Tid%2522%253a%252268cdfebb-157b-4846-ba2f-d196a9124ac0%2522%252c%2522Oid%2522%253a%25222aa70631-91e8-4b12-b01e-79459d41d6b5%2522%257d%26anon%3Dtrue&type=meetup-join&deeplinkId=195361cc-271b-4f88-be91-e82a4d57ad9d&directDl=true&msLaunch=true&enableMobilePage=true&suppressPrompt=true | O22: Carole Poiré | P22: carole.poire@universite-paris-saclay.fr | Q22: Paris Saclay | R22: Sophie Dondeyne
A23: 1 | B23: Les Midis de l'entrepreneuriat | C23: Entreprendre autrement : les modéles d'entrepreneuriat alternatifs | D23: Start in Saclay | G23: 45791 | I23: Distanciel | J23: Etudiants DU | K23: France | L23: Français | N23: https://teams.microsoft.com/dl/launcher/launcher.html?url=%2F_%23%2Fl%2Fmeetup-join%2F19%3Ameeting_NGZiZWIzZjctMWE0Yi00YmI4LTk2ZTctNjA5ZGM3NGMwOTgw%40thread.v2%2F0%3Fcontext%3D%257b%2522Tid%2522%253a%252268cdfebb-157b-4846-ba2f-d196a9124ac0%2522%252c%2522Oid%2522%253a%25222aa70631-91e8-4b12-b01e-79459d41d6b5%2522%257d%26anon%3Dtrue&type=meetup-join&deeplinkId=195361cc-271b-4f88-be91-e82a4d57ad9d&directDl=true&msLaunch=true&enableMobilePage=true&suppressPrompt=true | O23: Carole Poiré | P23: carole.poire@universite-paris-saclay.fr | Q23: Paris Saclay | R23: Sophie Dondeyne
A24: 1 | B24: Les Midis de l'entrepreneuriat | C24: L'aide au financement pour créer son entreprise | D24: France Active | F24: Animé par Chérif Abbou | G24: 45806 | I24: Distanciel | J24: Etudiants DU | K24: France | L24: Français | N24: https://teams.microsoft.com/dl/launcher/launcher.html?url=%2F_%23%2Fl%2Fmeetup-join%2F19%3Ameeting_NGZiZWIzZjctMWE0Yi00YmI4LTk2ZTctNjA5ZGM3NGMwOTgw%40thread.v2%2F0%3Fcontext%3D%257b%2522Tid%2522%253a%252268cdfebb-157b-4846-ba2f-d196a9124ac0%2522%252c%2522Oid%2522%253a%25222aa70631-91e8-4b12-b01e-79459d41d6b5%2522%257d%26anon%3Dtrue&type=meetup-join&deeplinkId=195361cc-271b-4f88-be91-e82a4d57ad9d&directDl=true&msLaunch=true&enableMobilePage=true&suppressPrompt=true | O24: Carole Poiré | P24: carole.poire@universite-paris-saclay.fr | Q24: Paris Saclay | R24: Sophie Dondeyne
A25: 2 | B25: Les Midis de l'entrepreneuriat | C25: Clôture de la série des webinaires | D25: Alumni | G25: 45812 | I25: Distanciel | J25: Etudiants DU | K25: France | L25: Français | N25: https://teams.microsoft.com/dl/launcher/launcher.html?url=%2F_%23%2Fl%2Fmeetup-join%2F19%3Ameeting_NGZiZWIzZjctMWE0Yi00YmI4LTk2ZTctNjA5ZGM3NGMwOTgw%40thread.v2%2F0%3Fcontext%3D%257b%2522Tid%2522%253a%252268cdfebb-157b-4846-ba2f-d196a9124ac0%2522%252c%2522Oid%2522%253a%25222aa70631-91e8-4b12-b01e-79459d41d6b5%2522%257d%26anon%3Dtrue&type=meetup-join&deeplinkId=195361cc-271b-4f88-be91-e82a4d57ad9d&directDl=true&msLaunch=true&enableMobilePage=true&suppressPrompt=true | O25: Carole Poiré | P25: carole.poire@universite-paris-saclay.fr | Q25: Paris Saclay | R25: Sophie Dondeyne
A26: 3 | B26: Master 1 et 2 en PI, droit du numérique et de l’espace | C26: L’objectif poursuivi au sein de la mention Droit de la propriété intellectuelle, du numérique et de l’espace consiste à former des juristes hautement spécialisés, en veillant à garantir l’adéquation des enseignements dispensés aux besoins de la pratique. Le déroulement de la formation est conçu pour permettre une pré-spécialisation de l’étudiant dès l’année de Master 1, afin de lui conférer, dans un deuxième temps, la possibilité d’opter, parmi un choix étendu de Masters 2, pour la spécialisation la plus conforme a ses affinités. | D26: Université Paris-Saclay | E26: Master 1 et 2 | F26: Cours magistraux, TP | H26: 2 ans | I26: Présentiel | J26: Etudiants | K26: France | L26: Français | O26: Antoine Latreille | P26: antoine.latreille@universite-paris-saclay.fr | Q26: Paris Saclay | R26: Antoine Latreille
A27: 1 | B27: M2 Droit de l’innovation et propriété industrielle | C27: Acquérir l’expertise nécessaire à l’exercice d’une activité professionnelle tournée vers l’innovation et la propriété industrielle, en phase avec la place éminente occupée par les sciences dures au sein du périmètre de l’Université Paris-Saclay. À l’issue de la formation, les étudiants doivent disposer : + de l’ensemble des connaissances théoriques en droit de la propriété industrielle (droit des brevets, droit des dessins et modèles, droit des marques…) et, plus largement, en droit des technologies et de la valorisation des actifs immatériels de l’entreprise (droit de la concurrence, droit des affaires, droit des télécommunications) ; + de connaissances dans les matières techniques, avec une formation pointue en informatique, réseaux et techniques numériques, afin de conférer aux étudiants une compréhension et une maîtrise des outils comme des principes (formation appliquée à l’informatique, connaissance des réseaux…) ; Acquérir les compétences indispensables à l’exercice de sa future profession. À cet égard, l’intervention de professionnels au sein de la formation et le stage obligatoire de trois à six mois garantissent une familiarité de l’étudiant avec la technique contractuelle utilisée en droit de la propriété industrielle, ou dans dans les produits et services numériques.. Les étudiants apprennent également à élaborer des stratégies de propriété intellectuelle, en intégrant dans leur réflexion le coût et la dimension internationale de la protection recherchée. Par ailleurs, la capacité de recherche de l’étudiant se trouve également mise à l’épreuve grâce à la rédaction d’un rapport de recherche. Enfin, les étudiants bénéficient de cours d’anglais juridique spécialisé, leur permettant de se familiariser avec la terminologie propre à ce champ disciplinaire. | D27: Université Paris-Saclay | E27: Master 1 | F27: Cours magistraux, TP | H27: 1 an | I27: Présentiel | J27: Etudiants | K27: France | L27: Français | O27: Antoine Latreille | P27: antoine.latreille@universite-paris-saclay.fr | Q27: Paris Saclay | R27: Antoine Latreille
A28: 1 | B28: M2 Droit de la création et du numérique | C28: Le Master 2 Droit de la création et du numérique (M2 DCN), fondé il y a trois décennies par le Professeur Pierre Sirinelli, est un diplôme pionnier dans l’étude de la confrontation du droit d’auteur aux nouvelles technologies. Il poursuit deux objectifs essentiels : + Offrir une spécialisation en droit d’auteur, saisi dans toutes ses dimensions, y compris les plus contemporaines (logiciels, jeux vidéo, bases de données), + Offrir une spécialisation en droit du numérique (droit des données personnelles, droit des contrats et de la responsabilité, droit pénal spécial des technologies, droit social et TIC). | D28: Université Paris-Saclay | E28: Master 2 | F28: Cours magistraux, TP | H28: 1 an | I28: Présentiel | J28: Etudiants | K28: France | L28: Français | O28: Antoine Latreille | P28: antoine.latreille@universite-paris-saclay.fr | Q28: Paris Saclay | R28: Antoine Latreille
A29: 1 | B29: M2 Droit des activités spatiales et des télécommunications | C29: Le master spécialité Droit des activités spatiales et des télécommunications (M2 DAST) a été créé en 2002 à la demande et avec le soutien des milieux professionnels pour satisfaire des secteurs en pleine expansion demandeurs de diplômés hautement qualifiés. Il représentait alors le premier diplôme au monde associant l’étude du droit de l’espace et des télécommunications. Il s’est depuis ouvert au secteur de l’aéronautique. Le M2 DAST propose une formation professionnalisante, interdisciplinaire et internationale à des étudiants désireux d’intégrer le secteur des technologies stratégiques : l’espace, l’aéronautique, le numérique et la défense. Le master repose sur une pédagogie fondée sur trois piliers. + Formation professionnalisante. Le contenu du Master est conçu en partenariat avec les grandes entreprises et institutions des secteurs de l’espace/aéronautique et des télécommunications/TIC. Les enseignements fondamentaux sont complétés par des séminaires pratiques. Le contact direct et permanent avec le marché du travail est favorisé par une équipe pédagogique majoritairement composée de professionnels (70% des intervenants), des cours dispensés par les futurs employeurs, dans les locaux d’entreprises et d’institutions prestigieuses (50% des cours), des visites et des voyages professionnels en France et à l’étranger, des projets professionnels conduits pour le compte des partenaires du Master, ainsi qu’un réseau international d’anciens étudiants. + Formation interdisciplinaire. La formation répond aux débouchés professionnels en associant le droit à l’étude d’autres disciplines : sciences, ingénierie, économie, gestion et sciences politiques. Le caractère interdisciplinaire de son équipe pédagogique et de ses promotions facilite l’intégration des diplômés au sein des entreprises et des institutions. Cette formation favorise de plus une compréhension rapide et approfondie des dossiers à traiter et une réelle capacité de dialogue avec toutes les composantes, notamment les départements techniques. + Formation internationale. La formation est ouverte sur l’Europe et le monde grâce à ses enseignements combinant une approche nationale et transnationale des problématiques, ses cours dispensés en français et en anglais, son équipe pédagogique multiculturelle (9 nationalités), ses promotions multinationales (le Master 2 a accueilli des étudiants issus de 71 pays) et ses activités à l’international. | D29: Université Paris-Saclay | E29: Master 2 | F29: Cours magistraux, TP | H29: 1 an | I29: Présentiel | J29: Etudiants | K29: France | L29: Français | O29: Antoine Latreille | P29: antoine.latreille@universite-paris-saclay.fr | Q29: Paris Saclay | R29: Antoine Latreille
A30: 1 | B30: M2 Propriété intellectuelle appliquée | C30: L’objectif est de dispenser un enseignement aussi bien théorique que pratique, hautement spécialisé en IP (séminaires de propriété littéraire et artistique, cours de propriété industrielle appliquée en droit des marques et des brevets, etc.) comme en IT (droit social et TIC, droit des données personnelles, pratique contractuelle spécialisée). L’équipe pédagogique est composée d’enseignants-chercheurs et de professionnels du secteur. Les étudiants sont aptes, dès l’obtention de leur diplôme, à occuper des postes à responsabilité dans le secteur de l’IP/IT. | D30: Université Paris-Saclay | E30: Master 2 | F30: Cours magistraux, TP | H30: 1 an | I30: Présentiel | J30: Etudiants | K30: France | L30: Français | O30: Antoine Latreille | P30: antoine.latreille@universite-paris-saclay.fr | Q30: Paris Saclay | R30: Antoine Latreille
A31: 1 | B31: M2 Propriété intellectuelle et droit des affaires numériques | C31: Le Master 2 Propriété intellectuelle et droit des affaires numériques (M2 PIDAN) forme les étudiants à maîtriser les défis juridiques actuels et futurs liés à l’essor des technologies de l’information, s’agissant aussi bien des enjeux théoriques que des pratiques contractuelles, judiciaires et techniques du secteur, afin de répondre à une demande croissante de la pratique contemporaine du droit des affaires national, européen et international. Les étudiants apprennent à identifier les stratégies juridiques de valorisation du patrimoine « numérique » et « intellectuel » des entreprises.A cette fin, le programme des séminaires allie enseignements fondamentaux en droit des affaires et cours spécialisés en propriété intellectuelle et droit du numérique. La formation met également l'accent sur l'acquisition de connaissances interdisciplinaires complémentaires en informatique et en économie notamment, ainsi que sur des enseignements dispensés en anglais. Selon le projet professionnel, les étudiants ont le choix, grâce aux options et aux travaux personnels, de renforcer leur spécialité soit en droit de la propriété intellectuelle soit en droit du numérique.Ce M2 permet de développer les compétences indispensables à une pratique professionnelle performante pour une insertion professionnelle rapide grâce au stage et aux exercices pratiques (négociation de contrats ou la rédaction de jeux d'écriture, participation aux concours de plaidoiries notamment).Ce Master 2 prépare également à une poursuite d'étude en doctorat en insistant sur la formation à la recherche individuelle (élaboration d'un mémoire de recherche de fin d'étude) et collective à l'occasion de chaque séminaire. Une attention particulière est portée à la maîtrise des outils de recherche et notamment des bases de données juridiques ainsi qu'à la participation à de nombreuses manifestations scientifiques.
A32: 1 | B32: M2 Propriété intellectuelle fondamentale et technologies numériques | C32: Le Master 2 / LLM Propriété intellectuelle fondamentale et technologies numériques (M2/LLM PIFTN) s’intègre dans l’offre de formation complémentaire de la mention Droit de la propriété intellectuelle et du numérique. Il en constitue le parcours international, grâce à un double partenariat, avec l’Université Laval (Québec) et avec l’Université Autonome de Madrid (Espagne). L’objectif est de former des juristes ayant des compétences pointues en Intellectual Property / Information Technology (IP/IT), donc à la fois en droit de la propriété intellectuelle, mais aussi en droit du numérique, dans une perspective résolument européenne et internationale. La formation débouche sur la délivrance, à l’issue d’une année d’étude, d’un double diplôme : un M2 de l’Université Paris-Saclay et un LLM de l’Université Laval (Québec) ou de l’Université Autonome de Madrid (Espagne), grâce à une mobilité étudiante (semestre 1 en France, semestre 2 au Québec ou en Espagne avec convention de reconnaissance mutuelle pour la moitié du programme). Le paiement des droits universitaires (sans surcoût) se fait dans le pays d’inscription initiale pour l’année entière. | D32: Université Paris-Saclay | E32: Master 2 | F32: Cours magistraux, TP | H32: 1 an | I32: Présentiel | J32: Etudiants | K32: France | L32: Français | O32: Antoine Latreille | P32: antoine.latreille@universite-paris-saclay.fr | Q32: Paris Saclay | R32: Antoine Latreille
A33: 1 | B33: FIE | C33: Filière Innovation-Entrepreneurs © (FIE) forme les élèves à entreprendre et innover grâce à une pédagogie par projet. 11 000 m2 dédiés à l'innovation et à l'entrepreneuriat technologique en photonique au Bâtiment 503. | D33: IOGS | E33: élèves avec la vision entrepreneur | H33: 1 à 4 ans | I33: Présentiel | J33: Etudiants | K33: France | L33: Français | O33: David Olivier Bouchez | P33: david-olivier.bouchez@institutoptique.fr | Q33: IOGS | R33: David Olivier Bouchez
A34: 1 | B34: Intelligence et Sécurité économiques | C34: Formation thématique | D34: SATT Paris Saclay | E34: Etudiants (Master, Doctorants) Chargé d'affaires valorisation Chercheurs Start-up PME/ETI | F34: Dispensée dans le Parcours Valo. La formation est enseignée sur demande / chaque thématique peut durer entre 1 heure et 4 heures | G34: Elle peut durer entre 1 heure et 4 heures | I34: Présentiel ou Distanciel | J34: Etudiants (Master, Doctorants) Chargé d'affaires valorisation Chercheurs Start-up PME/ETI | K34: France | L34: Français | O34: Stéphanie Oger-Roussel | P34: stephanie.oger-roussel@satt-paris-saclay.fr | Q34: SATT Paris Saclay | R34: Stéphanie Oger-Roussel
A35: 1 | B35: Veilles et renseignements | C35: Formation thématique | D35: SATT Paris Saclay | E35: Etudiants (Master, Doctorants) Chargé d'affaires valorisation Chercheurs Start-up PME/ETI | F35: La formation est enseignée sur demande / chaque thématique peut durer entre 1 heure et 4 heures | G35: Elle peut durer entre 1 heure et 4 heures | I35: Présentiel ou Distanciel | J35: Etudiants (Master, Doctorants) Chargé d'affaires valorisation Chercheurs Start-up PME/ETI | K35: France | L35: Français | O35: Stéphanie Oger-Roussel | P35: stephanie.oger-roussel@satt-paris-saclay.fr | Q35: SATT Paris Saclay | R35: Stéphanie Oger-Roussel
A36: 1 | B36: Open-innovation | C36: Formation thématique | D36: SATT Paris Saclay | E36: Etudiants (Master, Doctorants) Chargé d'affaires valorisation Chercheurs Start-up PME/ETI | F36: La formation est enseignée sur demande / chaque thématique peut durer entre 1 heure et 4 heures | G36: Elle peut durer entre 1 heure et 4 heures | I36: Présentiel ou Distanciel | J36: Etudiants (Master, Doctorants) Chargé d'affaires valorisation Chercheurs Start-up PME/ETI | K36: France | L36: Français | O36: Stéphanie Oger-Roussel | P36: stephanie.oger-roussel@satt-paris-saclay.fr | Q36: SATT Paris Saclay | R36: Stéphanie Oger-Roussel
A37: 1 | B37: Marketing de l'innovation | C37: Formation thématique | D37: SATT Paris Saclay | E37: Etudiants (Master, Doctorants) Chargé d'affaires valorisation Chercheurs Start-up PME/ETI | F37: La formation est enseignée sur demande / chaque thématique peut durer entre 1 heure et 4 heures | G37: Elle peut durer entre 1 heure et 4 heures | I37: Présentiel ou Distanciel | J37: Etudiants (Master, Doctorants) Chargé d'affaires valorisation Chercheurs Start-up PME/ETI | K37: France | L37: Français | O37: Stéphanie Oger-Roussel | P37: stephanie.oger-roussel@satt-paris-saclay.fr | Q37: SATT Paris Saclay | R37: Stéphanie Oger-Roussel
A38: 1 | B38: Propriété intellectuelle | C38: Formation thématique | D38: SATT Paris Saclay | E38: Etudiants (Master, Doctorants) Chargé d'affaires valorisation Chercheurs Start-up PME/ETI | F38: La formation est enseignée sur demande / chaque thématique peut durer entre 1 heure et 4 heures | G38: Elle peut durer entre 1 heure et 4 heures | I38: Présentiel ou Distanciel | J38: Etudiants (Master, Doctorants) Chargé d'affaires valorisation Chercheurs Start-up PME/ETI | K38: France | L38: Français | O38: Stéphanie Oger-Roussel | P38: stephanie.oger-roussel@satt-paris-saclay.fr | Q38: SATT Paris Saclay | R38: Stéphanie Oger-Roussel
A39: 1 | B39: Transfert de technologie | C39: Formation thématique | D39: SATT Paris Saclay | E39: Etudiants (Master, Doctorants) Chargé d'affaires valorisation Chercheurs Start-up PME/ETI | F39: La formation est enseignée sur demande / chaque thématique peut durer entre 1 heure et 4 heures | G39: Elle peut durer entre 1 heure et 4 heures | I39: Présentiel ou Distanciel | J39: Etudiants (Master, Doctorants) Chargé d'affaires valorisation Chercheurs Start-up PME/ETI | K39: France | L39: Français | O39: Stéphanie Oger-Roussel | P39: stephanie.oger-roussel@satt-paris-saclay.fr | Q39: SATT Paris Saclay | R39: Stéphanie Oger-Roussel
A40: 1 | B40: Business plan | C40: Formation thématique | D40: SATT Paris Saclay | E40: Etudiants (Master, Doctorants) Chargé d'affaires valorisation Chercheurs Start-up PME/ETI | F40: La formation est enseignée sur demande / chaque thématique peut durer entre 1 heure et 4 heures | G40: Elle peut durer entre 1 heure et 4 heures | I40: Présentiel ou Distanciel | J40: Etudiants (Master, Doctorants) Chargé d'affaires valorisation Chercheurs Start-up PME/ETI | K40: France | L40: Français | O40: Stéphanie Oger-Roussel | P40: stephanie.oger-roussel@satt-paris-saclay.fr | Q40: SATT Paris Saclay | R40: Stéphanie Oger-Roussel
A41: 1 | B41: Devenir entrepreneur | C41: Formation thématique | D41: SATT Paris Saclay | E41: Etudiants (Master, Doctorants) Chargé d'affaires valorisation Chercheurs Start-up PME/ETI | F41: La formation est enseignée sur demande / chaque thématique peut durer entre 1 heure et 4 heures | G41: Elle peut durer entre 1 heure et 4 heures | I41: Présentiel ou Distanciel | J41: Etudiants (Master, Doctorants) Chargé d'affaires valorisation Chercheurs Start-up PME/ETI | K41: France | L41: Français | O41: Stéphanie Oger-Roussel | P41: stephanie.oger-roussel@satt-paris-saclay.fr | Q41: SATT Paris Saclay | R41: Stéphanie Oger-Roussel
A42: 1 | B42: ESOS « Entreprenariat en Santé, Orientation et Sensibilisation » | C42: Le programme ESOS « Entreprenariat en Santé, Orientation et Sensibilisation » a été mis en place par la Faculté de Médecine Paris-Saclay, en collaboration avec la Graduate School Economie et Management , la Graduate School Life Sciences and Health, la Faculté de Pharmacie et le Hub PASREL de l’Université Paris-Saclay. | D42: Université Paris-Saclay | E42: Tous Niveaux | F42: Formation courte, préparatoire aux DU et Masters déjà existants et à venir dans le domaine de l’entrepreneuriat. Le programme est structuré en 3 phases : des webinaires de retour d'expérience d'entrepreneurs avec accès aux replays des webinaires des années précédentes, puis une phase de cours abordant les grands principes nécessaires à l'entrepreneuriat et enfin un accompagnement personnalisé pour les étudiants ayant un projet proposé par le Hub PASREL. | G42: Différentes durées selon le programme | I42: Distanciel | J42: Etudiants (Master, Doctorants) Chargé d'affaires valorisation Chercheurs Start-up PME/ETI | K42: France | L42: Français | N42: https://www.pasrel.universite-paris-saclay.fr/programme-esos/ | O42: Pascal CORBEL Laurence HOFFMANN | P42: pascal.corbel@universite-paris-saclay.fr laurence.hoffmann@universite-paris-saclay.fr | Q42: Paris Saclay | R42: Laurence Hoffmann
A43: 1 | B43: ESOS « Entreprenariat en Santé, Orientation et Sensibilisation » - TITRE ERRONE CETTE ACTION EST MENEE PAR LA GS LSH ET NE FAIT PAS PARTIE D'ESOS | C43: Cafés de la GS LSH - Webinaires | D43: Université Paris-Saclay | J43: Etudiants (Master, Doctorants) Chargé d'affaires valorisation Chercheurs Start-up PME/ETI | K43: France | L43: Français | N43: https://www.universite-paris-saclay.fr/actualites/cafes-de-la-gs-lsh | Q43: Paris Saclay | R43: Laurence Hoffmann
A44: 1 | B44: ESOS « Entreprenariat en Santé, Orientation et Sensibilisation » - TITRE ERRONE CETTE ACTION EST MENEE PAR LA GS LSH ET NE FAIT PAS PARTIE D'ESOS | C44: Les conversations de l'Espace éthique Île-de-France sur l’Intelligence artificielle - 27 janvier 2025 - Webinaire | J44: Etudiants (Master, Doctorants) Chargé d'affaires valorisation Chercheurs Start-up PME/ETI | K44: France | L44: Français | N44: https://www.espace-ethique.org/actualites/les-conversations-de-lespace-ethique-ile-de-france-saison-1 | Q44: Paris Saclay | R44: Laurence Hoffmann
A45: 1 | B45: Deeptech Tour Paris Saclay | C45: Deeptech Tour Paris Saclay. Au programme : présentation de l’écosystème, session de pitchs, témoignages inspirants, démonstrations de startups deeptech, cocktail, networking. | D45: BPI France et Université Paris-Saclay | E45: Tous Niveaux | F45: Pour sa troisième édition, le Deeptech Tour revient à Paris-Saclay pour mettre les projecteurs sur la deeptech. Cette tournée met à l'honneur les forces vives de la deeptech au sein des pôles académiques pour faire émerger des technologies de rupture à fort impact. | J45: Etudiants (Master, Doctorants) Chargé d'affaires valorisation Chercheurs Start-up PME/ETI | K45: France | L45: Français | R45: Cindy AUGUSTO DOS SANTOS
A46: 1 | B46: Global Women's Breakfast 2025 | C46: Global Women's Breakfast 2025 “Accelerating Equity in Science” - 11 février 2025 - Orsay | D46: Université Paris-Saclay | E46: Tous Niveaux | F46: Les Graduate Schools Chimie et Health and Drug Sciences vous invitent à partager un déjeuner à l'occasion du « International Day of Women and Girls in Science » autour de la thématique "Accelerating Equity in Science". Ce temps de rencontres et d'échanges se fera autour de 4 ateliers thématiques. Cet évènement participatif et constructif aura lieu le mardi 11 février 2025 de 12h30 à 14h30 dans le Hall - HM2 du Bâtiment Henri Moissan à Orsay. à Programme et inscription sous le lien suivant, cliquez ici ! | G46: 2 heures | I46: Présentiel | J46: Etudiants (Master, Doctorants) Chargé d'affaires valorisation Chercheurs Start-up PME/ETI | K46: France | L46: Français | P46: Inscriptions GWB 2025
A47: 1 | B47: Journées scientifiques GS HeaDS et OI Healthi | C47: Journées scientifiques GS HeaDS et OI Healthi - 11 et 12 février 2025 - Orsay. | D47: Université Paris-Saclay | E47: Tous Niveaux | F47: La Graduate School "Health and Drug Sciences" (GS HeaDS) et l'Objet Interdisciplinaire "Health and Therapeutic Innovation" (OI HEALTHI) vous invitent à participer à leurs Journées Scientifiques organisées conjointement les 11 et 12 février 2025 à l'Amphi Olivier KAHN au bâtiment Henri Moissan à Orsay. | G47: 2 jours | I47: Présentiel | J47: Etudiants (Master, Doctorants) Chargé d'affaires valorisation Chercheurs Start-up PME/ETI | K47: France | L47: Français
A48: 1 | B48: Paris-Saclay Summit - Choose Science | C48: Paris-Saclay Summit, un rendez-vous unique pour questionner l'essentiel et imaginer l'avenir. La 2e édition se tiendra les 12 et 13 février 2025 à EDF Lab. Du mercredi 12 au jeudi 13 février 2025 | D48: Université Paris-Saclay. Coorganisé par Le Point, La région Île-de-France et le Département de l’Essonne | E48: Tous Niveaux | G48: 2 jours | I48: Présentiel | J48: Tous public | K48: France | L48: Français | P48: Paris-Saclay Summit 2025 - Choose Science | R48: Cindy AUGUSTO DOS SANTOS
A49: 1 | B49: Genesis Light | C49: Formation de Sensibilisation à l’entrepreneuriat destinée aux chercheurs lauréats d’un Poc in Labs. | D49: IncubAlliance | E49: Tous Niveaux | G49: 7 jours | I49: Présentiel | J49: Exclusif pour les POC in Labs | K49: France | L49: Français | M49: 0 | O49: Arielle Santé | P49: https://www.incuballiance.fr/start-up/ | R49: Arielle Santé
A50: 1 | B50: Genesis Lab | C50: Pré-maturation pour challenger, dérisquer et structurer son projet de startup technologique. Elaboration d'une road map 360° | D50: IncubAlliance | E50: Tous Niveaux | G50: 3-4 mois | I50: Présentiel | J50: Acces sur Comité de séléction interne | K50: France | L50: Français | O50: Arielle Santé | P50: https://www.incuballiance.fr/start-up/ | R50: Arielle Santé
A51: 1 | B51: Impulse | C51: Incubation et accélération pour devenir une entreprise et accélérer sa commercialisation, sa levée de fonds, son recrutement. Favoriser et accélérer sa croissance | D51: IncubAlliance | E51: Tous Niveaux | F51: 3 critères de sélection : technologie, porteur de l'équipe et impact | G51: 18 mois à 5 ans | I51: Présentiel | J51: Acces sur Comité de séléction externe | K51: France | L51: Français | M51: 3000 | O51: Arielle Santé | P51: https://www.incuballiance.fr/start-up/ | R51: Arielle Santé
A52: 1 | B52: Des rencontres avec les autres start-up | C52: Incuballiance organise des Ateliers, rencontres entre start-up, témoignages, etc. | D52: IncubAlliance | E52: Tous Niveaux | F52: Selon le programme annuel | I52: Présentiel | J52: Porteurs de projets innovants | K52: France | L52: Français | O52: Arielle Santé | P52: https://www.incuballiance.fr/start-up/ | R52: Arielle Santé
A53: 1 | B53: Women in deeptech | C53: Le bootcamp pour passer de la recherche à l'action ! pour favoriser l’émergence de femmes entrepreneures dans la Deeptech au sein du cluster Paris-Saclay | D53: IncubAlliance | E53: Tous Niveaux | F53: Vision et valeurs ; Business model ; négociation ; propriété intellectuelle ; financements et pitch. | G53: 4 jours | I53: Présentiel | J53: Femme ingénieure, chercheuse, doctorante en poste ou étudiante | K53: France | L53: Français | O53: Arielle Santé | P53: https://www.incuballiance.fr/women-in-deeptech/ | R53: Arielle Santé
A54: 1 | B54: 10ème Journée d initiatives Pédagogiques | C54: Créer des objets de formation communs cercle vertueux de l'apprentissage et de la pédagogie. Innovation pédagogique. | D54: Université Paris-Saclay | E54: Tous Niveaux | F54: Journée de rencontre des enseignants et partage d'initiatives. | G54: 1/2 journée | I54: Hybride | J54: Tous public | K54: France | L54: Français | O54: DIP | P54: 10ème Journée d initiatives Pédagogiques - YouTube
A55: 1 | B55: Journées Innovation | C55: Plongez au cœur du processus d’innovation avec le MIT | D55: Université EVRY | E55: Tous Niveaux | F55: Cet événement met en lumière les acteurs clés qui font bouger notre écosystème : de l’accompagnement à l’idéation, en passant par le mentorat et le financement. | G55: 2 jours | H55: 2 jours | I55: Présentiel | J55: Tous public | K55: France | L55: Français | M55: 0 | N55: https://www.univ-evry.fr/index.php?id=19843 | O55: Président Université EVRY | P55: innovation@univ-evry.fr | Q55: Université Evry | R55: Gaëlle Bréau
A56: 1 | B56: Préparer son devenir professionnel - Parcours « Carrières de docteurs : Entrepreneuriat Deeptech » | C56: Bootcamp Starthèse Start'up Pitch-iD – Module «Innover en SHS : du labo au terrain”» | D56: Université Paris-Saclay | E56: Doctorants | F56: Ce module s’adresse aux doctorant·es en cours de thèse et aux docteur·es en sciences humaines et sociales (diplômé·es depuis moins de 5 ans, promotion 2020-2021), souhaitant se préparer et participer au challenge de pitch Startthèse Start'up Pitch-iD, qui aura lieu le 8 juillet. | G56: 1 jour | I56: Présentiel | J56: Doctorants | K56: France | L56: Français | N56: ADUM | O56: Roberta Camera Petriello | P56: roberta.camera-petriello@universite-paris-saclay.fr | Q56: Paris Saclay | R56: Maison du Doctorat
A57: 1 | B57: Préparer son devenir professionnel - Parcours « Carrières de docteurs : Entrepreneuriat Deeptech » | C57: Bootcamp Starthèse Start'up Pitch-iD – Module ”De la recherche à la scène :perfectionnez votre pitch” | D57: Université Paris-Saclay | E57: Doctorants | F57: Ce module s’adresse aux doctorant·es en cours de thèse et aux docteur·es (diplômé·es depuis moins de 5 ans, promotion 2020-2021), ayant déjà suivi les formations d’idéation ou avancée du parcours Entrepreneuriat Deeptech — ou toute autre formation équivalente dans ce domaine — et souhaitant se préparer à participer au challenge de pitch Starthèse Start’up Pitch-iD, qui se tiendra le 8 juillet. Les deux séances de formation vous permettrons de : ● valoriser sa recherche en un projet entrepreneurial ● articuler son projet autour d’un impact social ● communiquer et vulgariser efficacement pour convaincre | I57: Présentiel | J57: Doctorants | K57: France | L57: Français | N57: ADUM | O57: Roberta Camera Petriello | P57: roberta.camera-petriello@universite-paris-saclay.fr | Q57: Paris Saclay | R57: Maison du Doctorat
A58: 1 | B58: Préparer son devenir professionnel - Parcours « Carrières de docteurs : Entrepreneuriat Deeptech » | C58: Deeptech Entrepreneurship – Ideation Module: “Build a Successful Value Proposition' | D58: Université Paris-Saclay | E58: Doctorants | F58: By the end of the workshop, early-stage researchers will have gained key insights into scientific ideation and applied them to their own thesis or research results. This marks the first step toward bringing out an innovative product idea or launching a start-up, with dedicated and supportive guidance. | I58: Présentiel | J58: Doctorants | K58: France | L58: English | N58: ADUM | O58: Roberta Camera Petriello | P58: roberta.camera-petriello@universite-paris-saclay.fr | Q58: Paris Saclay | R58: Maison du Doctorat
A59: 1 | B59: Préparer son devenir professionnel - Parcours « Carrières de docteurs : Entrepreneuriat Deeptech » | C59: Parcours Entrepreneuriat Deeptech – Module Avancé «Construire un projet entrepreneurial deeptech » | D59: Université Paris-Saclay | E59: Doctorants | F59: L’objectif de cette formation est de vous permettre de maîtriser les étapes clés pour développer un projet entrepreneurial basé sur vos travaux de recherche. À travers des ateliers interactifs, vous aurez l’opportunité de : • Comprendre le processus de transition d’une technologie vers des marchés applicatifs ; • Structurer votre projet de manière claire et convaincante, afin de capter l’intérêt des organismes de financement dès les premières étapes ; • Élaborer une feuille de route (roadmap) sur 18 mois, alignée avec les actions stratégiques nécessaires pour propulser votre projet ; • Appréhender les mécanismes et les exigences des dossiers financiers afin de solliciter des fonds pour la maturation de votre projet. • Prendre conscience de l’expérience vécue durant 4,5 jours sous l’angle des compétences et appétences et se projeter dans la suite. | G59: 1 jour | I59: Présentiel | J59: Doctorants | K59: France | L59: Français | N59: ADUM | O59: Roberta Camera Petriello | P59: roberta.camera-petriello@universite-paris-saclay.fr | Q59: Paris Saclay | R59: Maison du Doctorat
A60: 1 | B60: Préparer son devenir professionnel - Parcours « Carrières de docteurs : Entrepreneuriat Deeptech » | C60: Parcours Entrepreneuriat Deeptech – Module « Docteur.e en Start-up » Session 15 | D60: Université Paris-Saclay | E60: Doctorants | F60: Ce module de deux jours permet de comprendre : • si la création d’entreprise est une voie professionnelle qui peut convenir ou non aux participants • les similitudes et les différences entre le travail d’un chercheur et celui d’un entrepreneur valorisant un actif scientifique ou technologique • les différents domaines clés sur lesquels doit travailler un entrepreneur pour construire la cohérence de son projet : maturité technologique, marchés, stratégie de propriété intellectuelle, financement, équipe… • l’écosystème du Plateau de Saclay qui peut aider les porteurs de projets • les raisons qui justifient l’engouement croissant depuis quelques années de la création d’entreprises “Deeptech” (issues de laboratoires de recherche) • comment construire une proposition de valeur à partir de résultats de recherche, afin de répondre à un besoin sociétal identifié et de valoriser concrètement les travaux menés au sein du laboratoire | G60: 2 jours | I60: Présentiel | J60: Doctorants | K60: France | L60: Français | N60: ADUM | O60: Roberta Camera Petriello | P60: roberta.camera-petriello@universite-paris-saclay.fr | Q60: Paris Saclay | R60: Maison du Doctorat
A61: 1 | B61: Parcours Valorisation de projets de recherche innovants | C61: Sensibilisation à la valorisation de la recherche : - 6 à 12 modules proposés : " Introduction à la valorisation de la recherche » ; « Sensibilisation à la Propriété intellectuelle (PI) » ; « Les aspects numériques de la PI » ; « Marketing de l’innovation » ; « Partenariats et organisation contractuelle »; « Transfert de technologie » ; « Management de projets » ; « Les bases de la négociation » ; « Veille et Intelligence économique et technologique » ; « Communiquer et agir en leader » ; « Sensibilisation au design" ; « Sensibilisation à la création d’entreprise » | D61: UPSaclay | E61: Doctorants tous niveaux, personnels administratifs, personnels des laboratoires, des GS, et extérieurs | F61: Journées | G61: 6 à 12 journées | H61: 6 à 12 jours | I61: Hybride | J61: Doctorants tous niveaux, personnels administratifs, personnels des laboratoires, des GS, et extérieurs | K61: France | L61: Français | N61: https://www.universite-paris-saclay.fr/parcours-de-formation-valorisation-de-projets-de-recherche-innovants-du-concept-au-marche | O61: Roberta Camera Petriello | P61: camille.queinnec@universite-paris-saclay.fr | R61: Camille Queinnec
A62: 1 | B62: Assemblée générales du Hub PASREL | C62: Une fois par an le Hub PASREL organise sa journée scientifique à l'occasion de son assemblée générale annuelle. C'est l'occasion de présentations et d'échanges autour des innovations technologiques en santé | D62: Université Paris Saclay | E62: Tous Niveaux | F62: Présentations et échanges autour des enjeux et des défis du developpement d'iinnovations technologiques en santé (propriété intelectuelle, études de marché, design, SHS, etc) | G62: 1/2 journée | I62: Présentiel | J62: Etudiants (Master, Doctorants) Chargé d'affaires valorisation Chercheurs Start-up PME/ETI | K62: France | L62: Français | M62: 0 | O62: Laurence Hoffman | P62: https://www.pasrel.universite-paris-saclay.fr/actualites/1ere-ag-hub-pasrel/ https://www.pasrel.universite-paris-saclay.fr/actualites/2e-ag-hub-pasrel/ | Q62: Université Paris Saclay | R62: Laurence Hoffmann
A63: 1 | B63: MaturAction | C63: “Maturaction” est un projet pédagogique qui a pour visée de former les étudiants à la gestion de projets innovants et à la création de start-up deeptech. L'objectif initial du programme initié dans le cadre de DTAPS est d'associer des étudiants à des projets innovants et concrets des laboratoires. Il s’agit, pour les étudiants, de réfléchir à la manière dont des résultats scientifiques pourraient devenir des applications industrielles ou des produits. Les étudiants évaluent différentes possibilités d’usages et valident leur potentiel via des études de marché et de faisabilité, des analyses de modèles d’affaires possibles, l’identification de modes de financements ou de verrous juridiques et réglementaires La poursuite de ce projet pédagogique se réalise à l'UVSQ en lien avec le référent entrepreneuriat de l'UVSQ | D63: Université de Versailles Saint-Quentin-en-Yvelines | E63: M1 et M2 | F63: Le programme est effectué en lien avec le référent entrepreneuriat de l'UVSQ | G63: Sourcing des projets au niveau des laboratoires par la direction de la valorisation Présentation au sein des formations Soutenance des étudiants | H63: Travail et échange avec le porteur scientifique sur la durée d'un semestre environ | I63: Travail et échange avec le porteur scientifique puis restitution dans le cadre d'une soutenance | J63: Etudiants, référent entrepreneuriat de l'UVSQ, direction de la valorisation, porteurs de projets concrets au sein des laboratoires de l'UVSQ | K63: France | L63: Français | M63: 0 | N63: https://www.uvsq.fr/maturaction-le-programme-de-formation-des-etudiants-a-lentrepreneuriat | O63: Direction de la valorisation de l'UVSQ Armelle Kouma | P63: valorisation@uvsq.fr | Q63: Différents sites de l'UVSQ | R63: Armelle Kouma
A64: 1 | B64: Start-up Games | C64: Afin de sensibiliser les étudiants à l'entrepreneuriat, des start up games sont proposés plusieurs fois par an. Il s'agit, sous forme de défi par équipe, dans un temps limité de prototyper un projet entrepreneurial selon un scénario et un objectif définis, autour d'une thématique précise. Les étudiants sont accompagnés tout au long de l’atelier par des entrepreneurs passionnés issus de l’incubateur Matrice, qui font découvrir les méthodologies de l’entrepreneuriat. | D64: Université de Versailles Saint-Quentin-en-Yvelines | E64: Master | F64: Les ateliers sont organisés par la direction de la valorisation de l'UVSQ avec le soutien de MATRICE | G64: Format sur 1/2 journée Environ 2 sessions par an | H64: 1/2 journée par session | I64: Défi entre équipes sur une thématique donnée dans un temps limité avec session de pitchs | J64: Les étudiants d'une filière désignée de l'UVSQ généralement de niveau Master | K64: France | L64: Français | M64: Accompagnement Matrice Prestation CROUS | N64: https://www.uvsq.fr/startup-games-lentrepreneuriat-sinvite-chez-les-etudiants-du-master-eads https://www.uvsq.fr/startup-game-sur-le-theme-management-qualite-securite-environnement-en-partenariat-avec-matrice | O64: Direction de la valorisation de l'UVSQArmelle Kouma | P64: valorisation@uvsq.fr | Q64: Différents sites de l'UVSQ | R64: Armelle Kouma
A65: 1 | B65: Journée EMERGENCE | C65: Journée EMERGENCE des projets de valorisation de la recherche @CentraleSupélec | D65: Centrale Supélec | E65: Tous publics | F65: Savoir si une idée ou une production issue de vos travaux a un potentiel de valorisation ? Faut-il s’engager dans la valorisation de la recherche ? Caractériser sa propriété intellectuelle: Brevet et/ou secrets ? Etude d’antériorité. Choisir un marché et décliner une proposition de valeur, Planifier son business development, Identifier les usagers et leurs besoins, Planifier : des prototypes aux produits, Quand est-on prêt à créer sa startup ? Effectuer son bilan de potentiel de valorisation, Être accompagné Journée le 7 octobre 2025 au Repaire (RdC Bat Bouygues) de 9h00 à 16h30 – Accueil à 8h30, repas inclus Inscription obligatoire avant le 1er octobre | G65: 1 journée | H65: 1 journée | I65: Présentiel | J65: Chercheur, doctorant, post-doc, IR, IE Centrale Supélec | K65: France | L65: Français | M65: 0 | N65: Journée EMERGENCE des projets de valorisation de la recherche @CentraleSupélec | O65: Bernard Yannou
A66: 1 | B66: Pépite PEIPS | C66: ETUDIANTS : Pôle de l'Entrepreneuriat et de l'Innovation à Paris-Saclay pour les étudiants | D66: Pépite PEIPS | E66: Etudiants | F66: PEPITE, le pôle dédié aux jeunes entreprenants | G66: Programme annuel | I66: Présentiel | J66: Etudiants | K66: France | L66: Français | M66: OUI | N66: https://www.universite-paris-saclay.fr/formation/entrepreneuriat-etudiant/pepite-peips | O66: Mehdia BELKAID – Coordinatrice entrepreneuriat étudiant - PEPITE PEIPS | Q66: https://pepite-peips.pepitizy.fr/fr/pepite | R66: Mehdia BELKAID
A67: 1 | B67: Les Midis de l'entrepreneuriat | C67: TITRE de la formation | D67: Qui est le formateur | E67: pour quel profil | F67: Description | G67: DATE | I67: Distanciel | J67: Etudiants DU | K67: France | L67: Français | N67: https://teams.microsoft.com/dl/launcher/launcher.html?url=%2F_%23%2Fl%2Fmeetup-join%2F19%3Ameeting_NGZiZWIzZjctMWE0Yi00YmI4LTk2ZTctNjA5ZGM3NGMwOTgw%40thread.v2%2F0%3Fcontext%3D%257b%2522Tid%2522%253a%252268cdfebb-157b-4846-ba2f-d196a9124ac0%2522%252c%2522Oid%2522%253a%25222aa70631-91e8-4b12-b01e-79459d41d6b5%2522%257d%26anon%3Dtrue&type=meetup-join&deeplinkId=195361cc-271b-4f88-be91-e82a4d57ad9d&directDl=true&msLaunch=true&enableMobilePage=true&suppressPrompt=true | O67: Carole Poiré
A68: 1 | B68: Les Midis de l'entrepreneuriat | C68: Un système microfluidique innovant pour la culture cellulaire | E68: Etudiants | F68: Des interventions thématiques de professionnel·le·s de l’écosystème entrepreneurial : les étapes de la création d’entreprise, trouver une idée, le design thinking, le business model… | G68: 45952 | I68: Distanciel | L68: Français | M68: Gratuit | R68: Sophie Seuron
A69: 1 | B69: Les Midis de l'entrepreneuriat | C69: Les clés pour être réactif pour innover en moins de 5 minutes | E69: Etudiants | F69: Des interventions thématiques de professionnel 05/11/25 | I69: Distanciel | L69: Français | M69: Gratuit | R69: Sophie Seuron
A70: 1 | B70: Les Midis de l'entrepreneuriat : Le développement et la construction de sa stratégie sur la propriété intellectuelle | E70: Etudiants | F70: Des interventions thématiques de professionnel 05/11/25 | G70: 45973 | I70: Distanciel | L70: Français | M70: Gratuit | R70: Sophie Seuron
A71: 1 | B71: Les Midis de l'entrepreneuriat | C71: Un procédé de revallorisation du gaspillage alimentaire en engrais et biocarburants | E71: Etudiants | F71: Des interventions thématiques de professionnel 05/11/25 | G71: 45980 | I71: Distanciel | L71: Français | M71: Gratuit | R71: Sophie Seuron
A72: 1 | B72: Les Midis de l'entrepreneuriat | C72: Quelle idée pour créer son entreprise ? | E72: Etudiants | F72: Des interventions thématiques de professionnel 05/11/25 | G72: 45987 | I72: Distanciel | L72: Français | M72: Gratuit | R72: Sophie Seuron
A73: 1 | B73: Les Midis de l'entrepreneuriat | C73: L'aide à la recherche documentaire pour réaliser une étude de marché | E73: Etudiants | F73: Des interventions thématiques de professionnel 05/11/25 | G73: 45994 | I73: Distanciel | L73: Français | M73: Gratuit | R73: Sophie Seuron
A74: 1 | B74: Les Midis de l'entrepreneuriat | C74: Une solution d'IA pour fluidifier la télé-ophtalmologie et détecter précocement les risques oculaires | E74: Etudiants | F74: Des interventions thématiques de professionnel 05/11/25 | G74: 46001 | I74: Distanciel | L74: Français | M74: Gratuit | R74: Sophie Seuron
A75: 1 | B75: Les Midis de l'entrepreneuriat | C75: Approche design | E75: Etudiants | F75: Des interventions thématiques de professionnel 05/11/25 | G75: 46008 | I75: Distanciel | L75: Français | M75: Gratuit | R75: Sophie Seuron
A76: 1 | B76: Les Midis de l'entrepreneuriat | C76: Une technologie optique deeptech pour révolutionner le traitement des maladies cutanées | E76: Etudiants | F76: Des interventions thématiques de professionnel 05/11/25 | G76: 46029 | I76: Distanciel | L76: Français | M76: Gratuit | R76: Sophie Seuron
A77: 1 | B77: Les Midis de l'entrepreneuriat | C77: Le modèlé économique | E77: Etudiants | F77: Des interventions thématiques de professionnel 05/11/25 | G77: 46037 | I77: Distanciel | L77: Français | M77: Gratuit | R77: Sophie Seuron
A78: 1 | B78: Les Midis de l'entrepreneuriat | C78: Un projet entrepreneurial qui automatise la création de semelles sur-mesure pour les rendre accessibles à tous | E78: Etudiants | F78: Des interventions thématiques de professionnel 05/11/25 | G78: 46043 | I78: Distanciel | L78: Français | M78: Gratuit | R78: Sophie Seuron
A79: 1 | B79: Les Midis de l'entrepreneuriat | C79: Débuter sans argent | E79: Etudiants | F79: Des interventions thématiques de professionnel 05/11/25 | G79: 46050 | I79: Distanciel | L79: Français | M79: Gratuit | R79: Sophie Seuron
A80: 1 | B80: Les Midis de l'entrepreneuriat | C80: Une plateforme pour aider les étudiants et jeunes actifs à maîtriser simplement leurs finances | E80: Etudiants | F80: Des interventions thématiques de professionnel·le·s de l’écosystème entrepreneurial : les étapes de la création d’entreprise, trouver une idée, le design thinking, le business model… | G80: 46057 | I80: Distanciel | L80: Français | M80: Gratuit | R80: Sophie Seuron
A81: 1 | B81: Les Midis de l'entrepreneuriat | C81: Les étapes de la création d'entreprise | E81: Etudiants | F81: Des interventions thématiques de professionnel 05/11/25 | G81: 46064 | I81: Distanciel | L81: Français | M81: Gratuit | R81: Sophie Seuron
A82: 1 | B82: Les Midis de l'entrepreneuriat | C82: Des ateliers culturels avec des animations fun et des activités fédératrices | E82: Etudiants | F82: Des interventions thématiques de professionnel 05/11/25 | G82: 46078 | I82: Distanciel | L82: Français | M82: Gratuit | R82: Sophie Seuron
... A86: 1 | B86: Les Midis de l'entrepreneuriat | C86: La démarche d'innovation | E86: Etudiants | F86: Des interventions thématiques de professionnel 05/11/25 | G86: 46113 | I86: Distanciel | L86: Français | M86: Gratuit | R86: Sophie Seuron
A87: 1 | B87: Design Spot | C87: Journée professionnelle : Design et recherche | E87: Tous | F87: L’APCI et le Design Spot de l’Université Paris-Saclay proposent une journée professionnelle sur les liens entre design, recherche, innovation et stratégie. | G87: 46091 | I87: Présentiel | L87: Français | M87: Gratuit | N87: https://www.designspot.fr/evenements/journee-professionnelle-design-et-recherche | O87: Yoann Montenot | P87: yoann.montenot@universite-paris-saclay.fr | R87: Sophie Seuron
A88: 1 | B88: Design Spot | C88: Raconter la bio-inspiration : de la recherche au grand public | E88: Tous | F88: Documentaire, animation, design et scénographie — projections et débat autour de l’exposition L’énergie du Vivant | G88: 46098 | I88: Présentiel | L88: Français | M88: Gratuit | N88: https://www.designspot.fr/ | O88: Yoann Montenot | P88: yoann.montenot@universite-paris-saclay.fr | R88: Sophie Seuron
A89: 1 | B89: Design Spot | C89: L'énergie du vivant : Événement de clôture et table ronde | E89: Tous | F89: L’exposition L’énergie du Vivant se conclut par une rencontre réunissant chercheurs et designers autour de la bio-inspiration et des sciences du vivant. | L89: Français | M89: Gratuit | N89: https://www.designspot.fr/evenements/evenement-de-cloture | O89: Yoann Montenot | P89: yoann.montenot@universite-paris-saclay.fr | R89: Sophie Seuron
A90: 1 | L90: Français | M90: Gratuit
A91: 1
A92: 1
A93: 1
A94: 1
A95: 1
A96: 1

Sheet Formations Externes
A1: Formations externes
A2: N | B2: Titre de la formation | C2: Objectifs pédagogiques du dispositif | D2: Etablissement | E2: Niveau | F2: Modalités pédagogiques / méthodologie | G2: Format | H2: Durée | I2: Modalité | J2: Public ciblé | K2: Pays | L2: Langue | M2: Coût | N2: web | O2: Contact | P2: Mail | Q2: Localisation | R2: CONTRIBUTEUR
A3: 1 | B3: Enseigner avec le jeu | C3: Découvrez la manière dont les jeux peuvent servir d’agents pivots pour l’engagement des apprenants et l’acquisition de compétences. | D3: Fun mooc Unicamp | E3: Micro certification | F3: On line | G3: 3 semaines | H3: 12 heures | I3: 10 h asynchrones, 2 h synchrones | J3: Aucun pré requis | K3: France | L3: Français | M3: 480 | N3: https://www.fun-mooc.fr/fr/cours/enseigner-avec-le-jeu/ | O3: Jérôme Legrix-Pagès | Q3: Université de Caen Normandie
A4: 2 | B4: Développer la posture entrepreneuriale | C4: Venez découvrir comment établir un plan d'action utile à l'atteinte de votre objectif de vous lancer avec la bonne posture dans votre projet d'entreprise ! | D4: Fun mooc Unicamp | E4: Micro certification | F4: On line | G4: 4 semaines | H4: 20 heures | I4: Asynchrone | J4: Aucun pré requis | K4: France | L4: Français | M4: 250 | N4: https://www.fun-mooc.fr/fr/cours/developper-la-posture-entrepreneuriale/ | O4: Armelle Basquin Marit | Q4: Université de Lille et du Littoral Côte d’Opale, Hubhouse et PEPITE.
A5: 3 | B5: Scénariser un parcours d'apprentissage | C5: Scénarisez votre enseignement pour gagner en cohérence pédagogique et permettre l'atteinte des objectifs fixés. | D5: Fun mooc Unicamp | E5: Micro certification | F5: On line | G5: 7 semaines | H5: 10 heures | I5: Asynchrone | J5: Aucun pré requis | K5: France | L5: Français | M5: 500 | N5: Scénariser un parcours d'apprentissage - Cours - FUN MOOC (fun-mooc.fr) | O5: Morgane Almerge, Michaël Canu | Q5: Université de Perpignan Via Domitia
A6: 4 | B6: Se former à la ludopédagogie | C6: Venez vous former à la ludopédagogie, découvrir l’utilisation du jeu dans un contexte de formation et comment l’intégrer. | D6: Fun mooc Unicamp | E6: Micro certification | F6: On line | G6: 6 semaines | H6: 30 heures | I6: 27 h asynchrones et 3 h synchrones | J6: Aucun pré requis | K6: France | L6: Français | M6: 750 | N6: https://www.fun-mooc.fr/fr/cours/se-former-a-la-ludopedagogie/ | O6: Jérôme Legrix-Pagès | Q6: Université de Caen Normandie
A7: 5 | B7: Oxford Venture Builder | C7: programme for all members of the University of Oxford - including students, staff, faculty members and researchers - who are looking to develop their business ideas, whether individually or as a team. | D7: Oxford | E7: Short programme | F7: On site. Three-day in-person bootcamp, Weekly sessions and mentorship, each Wednesday for five weeks, You will be invited to attend after hours sessions on various business-related topics. During this period, you will be matched with mentors to help you develop your ideas and tackle your challenges. Pitching night, pitch your ideas to our network. This is also a chance to access further support or funding. | G7: 5 semaines | J7: Aucun pré requis | K7: England | L7: English | M7: Gratuit | N7: https://www.sbs.ox.ac.uk/research/centres-and-initiatives/entrepreneurship-centre/oxford-venture-builder | O7: Oxford Saïd Entrepreneurship Centre _ EnSpire Oxford
A8: 6 | B8: Fabriquer l'innovation | C8: Comment se fabrique concrètement l’innovation, et en particulier l’innovation de rupture ? Ce Mooc mobilise des objets des collections du Musée des arts et métiers pour faire comprendre les processus de l’innovation. | D8: CNAM | E8: MOOC | F8: Ce cours est en accès libre. Il ne propose ni forum ni animation et ne délivre pas d'attestation, de badge ou de certificat. | G8: 5 semaines | H8: 8 heures | I8: Rythme: ~1h30/semaine | J8: Aucun pré requis | K8: France | L8: Français | M8: Gratuit | N8: https://www.fun-mooc.fr/fr/cours/fabriquer-linnovation/ | O8: FUN MOOC | Q8: CNAM
A9: 7 | B9: Intelligence artificielle pour et par les enseignants | C9: Explorer et soutenir l'utilisation éclairée de l'IA dans l'éducation. | D9: INRIA | E9: MOOC | F9: Dans le cadre du projet européen AI4T Artificial Intelligence for teachers | G9: 1 semaine | H9: 3 heures | J9: Aucun pré requis | K9: France | L9: Français | M9: Gratuit | N9: https://www.fun-mooc.fr/fr/cours/intelligence-artificielle-pour-et-par-les-enseignants-ai4t/
A10: 8 | B10: Travailler dans un fablab | C10: Habilitation pour travailler dans les machines du FABLAB CN2 de la Cité des Sciences | D10: Cité des Sciences | E10: Initiation et habilitation | F10: Ouverture du FABLAB en OpenLab Les mardis, mercredis, vendredis & samedis (hors vacances scolaires) Les mardis, mercredis, jeudis, vendredis & samedis (pendant vacances scolaires) de 14h30 à 17h30 Les initiations (Laser et Brodeuse) se font les mercredis et samedis à partir de 10h30 Pour les initiations 3D, merci de nous envoyer un email et de nous expliquer votre projet. Un jour et une heure de formation vous sera transmis après analyse de votre besoin. Les habilitations (Laser, 3D et Brodeuse) se font les vendredis à partir de 10h30 Les réservations des machines (avec habilitations) se font pendant les OpenLab | G10: 1 jour | H10: 3 heures | I10: Présentiel selon programmation | J10: Aucun pré requis | K10: France | L10: Français | M10: Gratuit | N10: https://carrefour-numerique.cite-sciences.fr/#!/ | O10: CITE DES SCIENCES | P10: https://mon-compte.cite-sciences.fr/inscription?origin=fabmanager | Q10: LA VILLETTE
A11: 9 | B11: Master PIC projet, innovation conception | C11: Le Master PIC s’articule autour de cinq grandes composantes qui incarnent à la fois son originalité et sa vocation : Le Projet de Master: une situation d’innovation concrète en entreprise où l’étudiant est intégré tout au long du cursus en temps réel Le tutorat: un dispositif pédagogique tripartite entre l’étudiant, un tuteur enseignant et le tuteur entreprise pour permettre d’articuler de manière continue les concepts théoriques et l’expérience pratique Des enseignements: sur les théories et méthodes toutes orientées sur l’innovation : projet, organisation, stratégie, financement, design, créativité, marketing,… Une expérience internationale, à la découverte d’un écosystème d’innovation dans un pays particulièrement emblématique en terme d’innovation Un cycle de visites industrielles, montrant la réalité de l’innovation, de la créativité à la production et la distribution, au sein de l’écosystème français. | D11: Ecole Politechnique | F11: La pédagogie combine des formats variés: cours magistral, étude de cas, pédagogie active, serious game, atelier, challenge, conférence, témoignage de praticiens, etc. | G11: 1 an | H11: Plein temps | I11: Présentiel. Learning by doing | K11: France | L11: Français | N11: https://masterpic.fr/cursus/programme/
A12: 10 | B12: OI iNanoTheRad | C12: Assemblée générale OI iNanoTheRad - 11 février 2025 - Villejuif L’Assemblée Générale d’iNanoTheRad aura lieu le 11 février 2025 de 10h à 12h à Gustave Roussy. Au programme, une présentation d’iNanoTheRad suivie de discussions thématiques sur les innovations en radiothérapie. | D12: Université Paris-Saclay
A13: 11 | B13: ICURe | C13: The Innovate UK ICURe Programme gives researchers the chance to turn ground-breaking research into investment-ready spin-out companies and license agreements. | D13: Innovate UK | F13: We provide funding and personalised support to test the commercial potential of an idea – while enabling researchers take their first steps into the world of business. | G13: 4 stages | H13: Au fil de l'eau | K13: UK | L13: English | N13: https://iuk-business-connect.org.uk/programme/icure/
A14: 12 | B14: investin.paris saclay | C14: Chef d’entreprise, un métier ? | D14: Le 30 | G14: Atelier | K14: France | L14: Français | N14: Chef d’entreprise, un métier ? – Communauté d'agglomération Paris-Saclay | O14: Pierre Henri MULTON | ASPASIE | P14: le30@paris-saclay.fr
A15: 13 | B15: Techinnov | C15: Les acteurs de l’innovation se réunissent autour de rendez-vous d’affaires le 27 mars 2025 au Parc Floral de Paris | D15: CCI Essonne CCI Ile de France | E15: Seminaire | F15: Hybride | G15: 1 jour | H15: JEUDI 27 MARS 2025 - PARC FLORAL DE PARIS | K15: France | L15: Français | N15: Techinnov 2025 | Une journée 100% business & innovation
A16: 14 | B16: MIT | C16: Free online courses from Massachusetts Institute of Technology | D16: USA | E16: MOOC | F16: MITx courses embody the inventiveness, openness, rigor and quality that are hallmarks of MIT, and many use materials developed for MIT residential courses in the Institute's five schools and 33 academic disciplines. Browse MITx courses below. | G16: On line | H16: Au fil de l'eau | K16: USA | L16: English | N16: https://www.edx.org/school/mitx
A17: 15 | B17: HARVARD | C17: Free online courses from Harvard | D17: USA | E17: MOOC | F17: 551 online free courses from Harvard | G17: On line | H17: Au fil de l'eau | K17: USA | L17: English | N17: https://pll.harvard.edu/catalog
A18: 16 | B18: HEC | C18: Free online courses from HEC | D18: France | E18: MOOC | F18: Nombreux cours gratuits et payants pour obtention d'un certificat | G18: On line | H18: Au fil de l'eau | K18: France | L18: Français | N18: https://www.hec.edu/fr/programmes-online/moocs
A19: 17 | B19: POLYTECHNIQUE | C19: Free online courses from Ecole Polytechnique | D19: France | E19: MOOC | F19: Présentation des cours en ligne gratuits et ouverts à tous de l'Ecole polytechnique | G19: On line | H19: Au fil de l'eau | K19: France | L19: Français | N19: https://www.polytechnique.edu/teaching-learning/
A20: 18 | B20: BPI France | C20: Les deeptech plateforme de formations | D20: France | E20: MOOC | F20: Développer ses compétences avec BPI France. Bpifrance Université vous accompagne ! L’entrepreneur ne doit jamais cesser d’apprendre tout au long de son parcours. Les objectifs ? Comprendre ses associés et ses équipes, rester à jour dans son domaine d’expertise, acquérir une nouvelle compétence clé pour le projet, comprendre ses partenaires… | G20: On line | H20: Au fil de l'eau | K20: France | L20: Français | N20: Se former à l’entrepreneuriat deeptech
A21: 19 | B21: AUNEGE Université Numérique | C21: Cours en ligne formation entrepreneuriat | D21: France | E21: MOOC | F21: La plate-forme Moodle de l'Université Numérique est un lieu de mutualisation de ressources éducatives libres. | G21: On line | H21: Au fil de l'eau | K21: France | L21: Français | N21: https://luniversitenumerique.fr/ressources/fun-ressources/
A22: 20 | B22: Réseau CURIE | C22: La journée des sensibilisateurs | D22: France | E22: Journée | F22: ÉDITION 2026 : Et si l'impact était la meilleure porte d'entrée vers la valorisation ? Sensibiliser autrement, détecter plus tôt. | G22: Présentiel | H22: Annuel | K22: France | L22: Français | N22: La journée des sensibilisateurs | Réseau C.U.R.I.E.
A23: 21 | B23: COURSERA | C23: Cours en ligne | D23: USA | E23: Variable | F23: Diférentes thématiques | G23: On line | H23: Au fil de l'eau | K23: USA | L23: English | N23: https://www.coursera.org/courseraplus/?utm_content=ad_b2c_emea_24-11_coursera-plus_fr-local_gg_fr_fr&utm_medium=sem&utm_source=gg&utm_campaign=b2c_emea_x_coursera_ftcof_courseraplus_cx_dr_bau_gg_sem_pr_fr_fr_m_hyb_24-11_x&campaignid=21962872997&adgroupid=172152784478&device=c&keyword=coursera&matchtype=e&network=g&devicemodel=&creativeid=723451402783&assetgroupid=&targetid=kwd-36262515261&extensionid=&placement=&gad_source=1&gad_campaignid=21962872997&gbraid=0AAAAADdKX6YTJ6uaPeGy9Rc6NYUuHMDzM&gclid=Cj0KCQjw54nRBhDCARIsAMcY_SDTW7KIMyFXNQE48TIaiUqif04XJ81SyKLJK1Nuu8IWfhP3BOGMueEaAg0QEALw_wcB
A24: 22
A25: 23

Sheet Formateurs
A1: Formateurs et autres ressources
A2: N | B2: Type | C2: Description | D2: Modalités pédagogiques / méthodologie | E2: Etablissement | F2: Fonction | G2: Type | H2: Nom Contact | I2: Mail | J2: Site Web | K2: Rôle PUI | L2: CONTRIBUTEUR
A3: 1 | B3: Droit des contrats | C3: Parcours Valo. Formation en propriété intellectuelle et contrats de recherche | E3: Université Paris-Saclay | F3: Responsable Pôle Partenariat Valorisation (PPV) DIREV / enseignante master | G3: Interne | H3: Soizic Lefeuvre, Camille Quenec | I3: soizic.lefeuvre@universite-paris-saclay.fr | K3: Fondateur
A4: 2 | B4: Sensibilisation à la PI | C4: Parcours Valo | D4: module théorique et cas pratique | E4: Université Paris-Saclay | F4: DIREV, juristes - agents formateurs | G4: Interne | H4: Salomé Petroff, Charlotte Guerel | I4: camille.queinnec@universite-paris-saclay.fr | J4: https://www.universite-paris-saclay.fr/parcours-de-formation-valorisation-de-projets-de-recherche-innovants-du-concept-au-marche | K4: Fondateur | L4: CQ
A5: 3 | B5: Transferts de technologies | C5: Parcours Valo | D5: module théorique et cas pratique | E5: Université Paris-Saclay | F5: DIREV, chargés affaires - agents formateurs | G5: Interne | H5: Antoine Brian, Elisa Paredes | I5: camille.queinnec@universite-paris-saclay.fr | J5: https://www.universite-paris-saclay.fr/parcours-de-formation-valorisation-de-projets-de-recherche-innovants-du-concept-au-marche | K5: Fondateur | L5: CQ
A6: 4 | B6: Autres modules Parcours Valo | C6: Parcours Valo | D6: module théorique et cas pratique | E6: Université Paris-Saclay | F6: personnels du CERDI, de la SATT, d'IncubAlliance, du Design Spot, | G6: Interne | H6: PV25 | I6: camille.queinnec@universite-paris-saclay.fr | J6: https://www.universite-paris-saclay.fr/parcours-de-formation-valorisation-de-projets-de-recherche-innovants-du-concept-au-marche | K6: Fondateur | L6: CQ
A7: 5 | B7: ERC | C7: Mette Skadstraat Consultante pour la formation et préparation à l'ERC | D7: Webinaires, préparation aux oraux, relectures de documents, oraux blancs | E7: Yellow research | F7: Consultant | G7: Externe | H7: Amanda Nieto | J7: https://www.yellowresearch.nl/ | K7: Autre
A8: 6 | B8: Éthique et innovation : comment intégrer l'IA Act dans sa stratégie d'innovation ? | C8: AI ACT Cette session en partenariat avec le Hub France IA vise à fournir aux TPE, PME et ETI les outils essentiels pour se lancer dans l'aventure de l'IA avec confiance. | D8: A créer | E8: Hub France IA | F8: Responsable des affaires européennes et réglementaires | G8: Externe | H8: Chloé PLÉDEL | J8: BIG BPI Masterclass | K8: Autre
A9: 7 | B9: Éthique et innovation : comment intégrer l'IA Act dans sa stratégie d'innovation ? | C9: Cette session en partenariat avec le Hub France IA vise à fournir aux TPE, PME et ETI les outils essentiels pour se lancer dans l'aventure de l'IA avec confiance. | D9: A créer | E9: Bpifrance | F9: Responsable de l'acceleration IA - Direction du digital | H9: Pierre JARRIJON | J9: https://evenements.bpifrance.fr/big-2024/fr/onlinesession/8e167e6f-812d-ef11-86c3-002248863087 | K9: Autre
A10: 8 | B10: Master / Licence | C10: Droit du numérique et de l’espace/ Droit de l’innovation et propriété industrielle/Droit, Sciences & Innovation | D10: En attente infos | E10: Université Paris-Saclay | F10: Vice-président Patrimoine & Infrastructures/Doyen honoraire/ Chercheur au Cerdi | G10: Interne | H10: Antoine Latreille | I10: antoine.latreille@universite-paris-saclay.fr
A11: 9 | B11: Créer un cours sur FUN | C11: Création de MOOC et SPOOC France Universités Numérique | E11: France Universités Numérique | F11: Directeur technique et chef de projet | G11: Externe | H11: Cédric Bassette | I11: cedric.bassette@fun-mooc.fr | J11: https://www.fun-mooc.fr/fr/ | K11: Autre
A12: 10 | B12: Doctorants | C12: Médiation scientifique | D12: jours / rémunérés sur le même barême 32 jours au plus | E12: Université Paris-Saclay | F12: Doctorants étudiants
A13: 11 | B13: =+'Formations PUI'!C7 -> Créer sa landing page sans savoir coder en 48 heures | D13: A créer | E13: =+'Formations PUI'!D7 -> Diogale | G13: Externe | H13: =+'Formations PUI'!F7 -> Animé par Doudou Diof | I13: Contacter Sophie Dondeyne DFR | K13: Autre
A14: 12 | B14: =+'Formations PUI'!C8 -> Quelle idée pour créer ton entreprise ? | D14: A créer | E14: =+'Formations PUI'!D8 -> Innowide | G14: Externe | H14: =+'Formations PUI'!F8 -> Animé par Damien Cuoq | I14: Contacter Sophie Dondeyne DFR | K14: Autre
A15: 13 | B15: =+'Formations PUI'!C9 -> De l'idée à l'action : concevoir et lancer votre startup | D15: A créer | E15: =+'Formations PUI'!D9 -> Start in Saclay | G15: Interne | H15: =+'Formations PUI'!F9 -> 0 | I15: Contacter Sophie Dondeyne DFR | K15: Fondateur
A16: 14 | B16: =+'Formations PUI'!C10 -> Les conseils pour avoir un pitch convaincant | D16: A créer | E16: =+'Formations PUI'!D10 -> Association EGEE | G16: Externe | H16: =+'Formations PUI'!F10 -> 0 | I16: Contacter Sophie Dondeyne DFR | K16: Autre
A17: 15 | B17: =+'Formations PUI'!C11 -> Les outils à connaitre pour son projet d'entreprise | D17: A créer | E17: =+'Formations PUI'!D11 -> Design Spot | G17: Interne | H17: =+'Formations PUI'!F11 -> Annimé par Yoann Montenot | I17: Contacter Sophie Dondeyne DFR | K17: Fondateur
A18: 16 | B18: =+'Formations PUI'!C12 -> Le modéle économique | D18: A créer | E18: =+'Formations PUI'!D12 -> Université Paris-Saclay | G18: Interne | H18: =+'Formations PUI'!F12 -> 0 | I18: Contacter Sophie Dondeyne DFR | K18: Fondateur
A19: 17 | B19: =+'Formations PUI'!C13 -> Entreprendre en deeptech : défis et opportunités | D19: A créer | E19: =+'Formations PUI'!D13 -> Start in Saclay | G19: Interne | H19: =+'Formations PUI'!F13 -> 0 | I19: Contacter Sophie Dondeyne DFR | K19: Fondateur
A20: 18 | B20: =+'Formations PUI'!C14 -> Aide à la recherche documentaire pour réaliser une étude de marché | D20: A créer | E20: =+'Formations PUI'!D14 -> Université Paris-Saclay | G20: Interne | H20: =+'Formations PUI'!F14 -> Animé par Imelda Lemoing | I20: Contacter Sophie Dondeyne DFR | K20: Fondateur
A21: 19 | B21: =+'Formations PUI'!C15 -> Débuter sans argent | D21: A créer | E21: =+'Formations PUI'!D15 -> Graines de conseil | G21: Externe | H21: =+'Formations PUI'!F15 -> Animé par Bertrand De Saint Viance | I21: Contacter Sophie Dondeyne DFR | K21: Autre
A22: 20 | B22: =+'Formations PUI'!C16 -> Les étapes de la création d'entreprise | D22: A créer | E22: =+'Formations PUI'!D16 -> Vallée Sud Grand Paris | G22: Externe | H22: =+'Formations PUI'!F16 -> Animé par Farrouk Khenoussi | I22: Contacter Sophie Dondeyne DFR | K22: Autre
A23: 21 | B23: =+'Formations PUI'!C17 -> Le développement et la construction de sa stratégie sur la propriété intelectuelle | D23: A créer | E23: =+'Formations PUI'!D17 -> INPI | G23: Externe | H23: =+'Formations PUI'!F17 -> Animé par Sophie Djega Mariadassou | I23: Contacter Sophie Dondeyne DFR | K23: Autre
A24: 22 | B24: =+'Formations PUI'!C18 -> Accélérateurs et incubateurs : catalyseurs de réussite | D24: A créer | E24: =+'Formations PUI'!D18 -> Start in Saclay | G24: Interne | H24: =+'Formations PUI'!F18 -> 0 | I24: Contacter Sophie Dondeyne DFR | K24: Fondateur
... A26: 24 | B26: =+'Formations PUI'!C20 -> Accélérer la croissance : les clés pour réussir sa levée de fonds | D26: A créer | E26: =+'Formations PUI'!D20 -> Start in Saclay | G26: Interne | H26: =+'Formations PUI'!F20 -> 0 | I26: Contacter Sophie Dondeyne DFR | K26: Fondateur
A27: 25 | B27: =+'Formations PUI'!C21 -> Les stratégies marketing | D27: A créer | E27: =+'Formations PUI'!D21 -> Association EGEE | G27: Externe | H27: =+'Formations PUI'!F21 -> Animé par Jacques Bonnement | I27: Contacter Sophie Dondeyne DFR
A28: 26 | B28: =+'Formations PUI'!C22 -> Startups à impact : entreprendre pour un monde meilleur | D28: A créer | E28: =+'Formations PUI'!D22 -> Start in Saclay | G28: Interne | H28: =+'Formations PUI'!F22 -> 0 | I28: Contacter Sophie Dondeyne DFR | K28: Fondateur
A29: 27 | B29: =+'Formations PUI'!C23 -> Entreprendre autrement : les modéles d'entrepreneuriat alternatifs | D29: A créer | E29: =+'Formations PUI'!D23 -> Start in Saclay | G29: Interne | H29: =+'Formations PUI'!F23 -> 0 | I29: Contacter Sophie Dondeyne DFR | K29: Fondateur
A30: 28 | B30: =+'Formations PUI'!C24 -> L'aide au financement pour créer son entreprise | D30: A créer | E30: =+'Formations PUI'!D24 -> France Active | G30: Externe | H30: =+'Formations PUI'!F24 -> Animé par Chérif Abbou | I30: Contacter Sophie Dondeyne DFR | K30: Autre
A31: 29 | B31: Serious game: l'année de l'innovation | D31: Avec de droits de licence d'utilisation | E31: Centrale Supelec | G31: Interne | H31: Bernard Yannou
A32: 30 | B32: Ikigai - Games for Citizens | C32: Innovation par les jeux | D32: A créer | E32: Ikigai - Games for Citizens | F32: Responsable de formation, d'animation de communauté et de prospection | G32: Externe | H32: Florian Delcourt | I32: formation.animation@ikigai.games | J32: https://www.gfc.ikigai.games/ | K32: Autre | L32: tel 0620853103
A33: 31 | B33: Design Thiking | C33: Atelier spécifique sur le Design Thinking l'Atelier Universel | D33: Atelier | E33: L'Atelier Universel | G33: Externe | H33: Xavier Auffret | I33: xavier.auffret@atelier-universel.com | J33: atelier-universel.com
A34: 32 | B34: Design Thiking | C34: Le Design Thinking légèrement abordé lors de l'atelier "c'est quoi le design ?". | D34: Atelier | E34: Design Spot | F34: Directeur Design Spot | G34: Interne | H34: Yoann Montenot | I34: yoann.montenot@universite-paris-saclay.fr
A35: 33 | B35: Soft skills | C35: Mon CV en 180 segondes JIP 2026 | D35: Atelier | E35: MCU Biotechnologies - Association France Biotech | F35: Directrice adjointe Formation Graduate School Health and Drug Sciences | G35: Interne | H35: Isabelle Turbica | I35: isabelle.turbica@universite-paris-saclay.fr
A36: 34 | B36: Soft skills | C36: Mon CV en 180 segondes JIP 2026 | D36: Atelier | E36: GS LSH- Association France Biotech | F36: GS LSH | G36: Interne | H36: Patricia Uguen | I36: patricia.uguen@universite-paris-saclay.fr
A37: 35
A38: 36
A39: 37
A40: 38
A41: 39
A42: 40
A43: 41
A44: 42
A45: 43
A46: 44

Sheet Lieuxinnovation
A1: Lieux pour l'innovation
A2: N | B2: Type | C2: Description | D2: Etablissement | E2: Lien | F2: Nom Contact | G2: Mail | H2: CONTRIBUTEUR
A3: 1 | B3: 21st | C3: l’accélérateur de start-up de CentraleSupélec, accompagne les élèves-ingénieures et élèvesingénieurs, les étudiantes et étudiants dans le développement et l’évolution de leurs projets. | D3: Centrale Supélec | E3: https://lafabrique.centralesupelec.fr/ | F3: Bernard Yannou | G3: bernard.yannou@centralesupelec.fr
A4: 2 | B4: 503 | C4: 11 000 m2 dédiés à l'innovation et à l'entrepreneuriat technologique en photonique. Lié directement avec la Filière Innovation-Entrepreneurs © (FIE) forme les élèves à entreprendre et innover grâce à une pédagogie par projet. | D4: IOGS | E4: https://www.institutoptique.fr/entreprises-et-innovation/les-centres-entrepreneuriaux-503/formation-par-lentrepreunariat#:~:text=La%20FIE%2C%20c'est%20%3A&text=Un%20enseignement%20sur%20mesure%20propos%C3%A9,l'entrepreneuriat%20technologique%20en%20photonique. | F4: David Olivier Bouchez
A5: 3 | B5: Design spot | C5: Le point de rencontre entre recherche, innovation et design à Paris-Saclay. | D5: Université Paris Saclay | E5: https://www.designspot.fr/ | F5: Yoann Montenot | G5: yoann.montenot@universite-paris-saclay.fr | H5: Marine Perez
A6: 4 | B6: C2N | C6: Plateforme d'Innovation en Micro et Nano-Technologies (PIMENT). La plateforme a été organisée en quatre pôles principaux correspondant aux technologies clés : la lithographie, la gravure, le dépôt de couches minces et la mesure et le contrôle. La plateforme PIMENT, comme le reste de la Centrale de Technologie, fait partie de RENATECH, le réseau national des Centrales de Technologies du domaine des micro-nanotechnologies piloté par le CNRS. | D6: Université Paris Saclay | E6: https://piment.c2n.universite-paris-saclay.fr/fr/ | F6: Benoît Belier
A7: 5 | B7: LUMEN | C7: Bibliothèque, salles el lieux de réunion. Expositions, médiation scientifique, accès à des ouvrages tout public tels des BD, des romans ou des guides touristiques, et spécialisés pour la recherche scientifique | D7: Université Paris Saclay | E7: https://www.destination-paris-saclay.com/fr/fiche/equipement/le-lumen-gif-sur-yvette_TFO6737489/ | F7: CONTACT GENERIQUE | G7: evenementiel.lumen@universite-paris-saclay.fr | H7: Attention la page principale n'est pas accessible donc le lien est sur destination Paris Saclay
A8: 6 | B8: LE FABLAB DU CN2 | C8: La Cité des sciences Paris. Initiés par Neil Gershenfeld, professeur au Massachusetts Institute of Technology (MIT), les Fab Labs (Fabrication Laboratory) sont des lieux ouverts à tou·te·s et destinés à l’apprentissage et l’expérimentation. | D8: Cité des sciences Paris | E8: https://www.cite-sciences.fr/fr/au-programme/lieux-ressources/carrefour-numerique2/fab-lab
A9: 7 | B9: Bâtiment 440 – Diapason aux besoins des projets. | C9: Diapason offre la location de ses locaux, nus et en l’état, pour une parfaite adaptabilité aux besoins des projets.
A10: 8 | B10: Fablab Paris Saclay | C10: Digiscope est un réseau de plateformes pour la visualisation interactive de grandes quantités de données et de calculs complexes. Laboratoire de fabrication numérique de l’université, est dédié à la recherche scientifique et à son support, à l’enseignement universitaire et à la formation des professionnels | D10: Université Paris Saclay | E10: http://www.digiscope.fr/fr | F10: Romain di Vozzo | G10: romain.di-vozzo@universite-paris-saclay.fr | H10: info@digiscope.fr
A11: 9 | B11: La Fabrique | C11: Fablab pour les étudiants et enseignants. Prototypage, acculturation, expertise et accompagnement. le fablab de CentraleSupélec, accompagne les porteurs de projets dans leurs phases d’analyse, d’études, de conception, de prototypage-maquettage et d’industrialisation. | D11: Centrale Supélec | E11: https://lafabrique.centralesupelec.fr/ | F11: Bernard Yannou | G11: bernard.yannou@centralesupelec.fr
A12: 10 | B12: Food’InnLab | C12: la plateforme de collaboration d’AgroParisTech, associe recherche, enseignement et start-up. | D12: AgroParisTech | F12: Grégoire Burgé
A13: 11 | B13: Genopole | C13: est le premier biocluster en France dédié aux biotechnologies appliquées à la santé, l’environnement, la foodtech, l’agritech et la bio-industrie.
A14: 12 | B14: IncubAlliance | C14: L’incubateur deeptech du territoire Paris-Saclay, soutient les projets d’entrepreneuriats technologiques innovants provenant de l’université ou d’entreprises. | D14: IncubAlliance | F14: Arielle Santé
A15: 13 | B15: Innov’Lab | C15: C'est le lieu de conseil en conception et fabrication, et d’assistance à la création de prototypes
A16: 14 | B16: Inria Start-up Studio | C16: Inria Start-up Studio est le programme d’accompagnement et de financement pour les start-up deeptech numériques. | D16: INRIA
A17: 15 | B17: L’Institut Vedecom – mobiLAB | C17: L’Institut Vedecom – mobiLAB comprend des espaces de recherche et de formation, des ateliers et des laboratoires entièrement dédiés aux nouvelles mobilités.
A18: 16 | B18: Photonic Fablab | C18: Photonic Fablab est une plateforme de prototypage de l’Institut d’Optique Graduate School dédiée au développement et à la phase de pré-industrialisation d’un produit. | F18: David Olivier Bouchez
A19: 17 | B19: PASREL | C19: PASREL est un réseau de laboratoires de recherche de l’Université Paris-Saclay (objet interdisciplinaire Hub PASREL), d’établissements de santé et une équipe d’animation pilotée par le professeur Vincent Lebon. En 2027, cette équipe d’animation s’installera dans le bâtiment PASREL nouvellement construit à côté de l’Hôpital de Paris-Saclay | F19: Vincent Lebon
A20: 18 | B20: La scène de recherche | C20: La Scène de recherche est un théâtre professionnel de 160 places, niché au cœur de l'ENS Paris-Saclay. Elle fait dialoguer les arts, les sciences et les technologies à travers une programmation foisonnante en salle et hors les murs (théâtre, danse, magie nouvelle, cirque…), des ateliers de pratiques artistiques pour tous les publics et des projets d’action culturelle dans les établissements scolaires du territoire. | E20: https://ens-paris-saclay.fr/scene-de-recherche | G20: + 33 1 81 87 50 00
A21: 19 | B21: Territoire Paris Saclay | C21: Cartographie des lieux d’innovation et des start-up de Paris-Saclay | D21: EPAPS | E21: http://paris-saclay-startup.com/map/index.html#/ | F21: Frédéric Devaivre | G21: frederic.devaivre@oin-paris-saclay.fr
A22: 20 | B22: Paris-Saclay Hardware Accelerator (PSHA) | C22: Propose des programmes immersifs et intégrés afin d’accélérer dans les meilleures conditions la réalisation des projets | D22: PSHA | E22: https://www.lafrenchfab.fr/entreprise/paris-saclay-hardware-accelerator/ | F22: MOINAT Alain | G22: contact@psha.fr | H22: +33 (0)1 64 48 32 32 | I22: Saulx les Chartreux
A23: 21 | B23: Farm'inlab

Sheet Equipements
A1: Equipements
A2: N | B2: Type | C2: Etablissement | D2: Localisation | E2: Page référence | F2: Nom Contact | G2: Mail | H2: CONTRIBUTEUR
A3: 1 | B3: Tous les équipements | C3: Université Paris Saclay | D3: DIREV POLE PAST | E3: https://www.pluginlabs-universiteparissaclay.fr/ | F3: Bruno Bost
A4: 2 | B4: Imprimante 3 D | C4: Centrale Supelec | D4: Batiment central La Fabrique
A5: 3 | B5: Lithographies électroniques, optiques/UV et émergentes | C5: CNRS Paris saclay | D5: C2N - Plateforme PIMENT | E5: https://piment.c2n.universite-paris-saclay.fr/fr/ | F5: Benoît Belier
A6: 4 | B6: Dépôts métal et diélectrique, croissance électrolytique, traitements thermiques | C6: CNRS Paris saclay | D6: C2N - Plateforme PIMENT | E6: https://piment.c2n.universite-paris-saclay.fr/fr/ | F6: Benoît Belier
A7: 5 | B7: Gravures sèche et humide, chimie | C7: CNRS Paris saclay | D7: C2N - Plateforme PIMENT | E7: https://piment.c2n.universite-paris-saclay.fr/fr/ | F7: Benoît Belier
A8: 6 | B8: Microscopies électroniques et optiques, Back-End, characterisations | C8: CNRS Paris saclay | D8: C2N - Plateforme PIMENT | E8: https://piment.c2n.universite-paris-saclay.fr/fr/ | F8: Benoît Belier
A9: 7 | B9: Equipements et machines du FABLAB CN2 (découpeuses laser, imprimantes 3D, brodeuses, podcast , son...) | C9: Cite des Sciences | D9: La Villette | E9: https://carrefour-numerique.cite-sciences.fr/#!/
A10: 8 | B10: WILDER: Mur d'écrans très haute résolution multitactile avec système de suivi de mouvements. | C10: Université Paris Saclay | D10: Fablab Paris Saclay | E10: http://www.digiscope.fr/fr/platforms/wilder
A11: 9 | B11: WILD; Mur d'écrans ultra haute résolution avec système de suivi de mouvements. | C11: Université Paris Saclay | D11: Fablab Paris Saclay | E11: http://www.digiscope.fr/fr/platforms/wild
A12: 10 | B12: EVE: Très grand espace immersif, multi-sensorimoteur et multi-utilisateur | C12: Université Paris Saclay | D12: Fablab Paris Saclay | E12: http://www.digiscope.fr/fr/platforms/eve
A13: 11 | B13: PIXLS: Grand mur d'écrans multitactile | C13: Université Paris Saclay | D13: Fablab Paris Saclay | E13: http://www.digiscope.fr/fr/platforms/pixls
A14: 12 | B14: IRIS : Mur d'écrans multitactile de taille intermédiaire. | C14: Université Paris Saclay | D14: Fablab Paris Saclay | E14: http://www.digiscope.fr/fr/platforms/iris
A15: 13 | B15: SHIVA : Grand mur d'image stéréoscopique | C15: Université Paris Saclay | D15: Fablab Paris Saclay | E15: http://www.digiscope.fr/fr/platforms/shiva
A16: 14 | B16: Mandelbrot: Très grand écran stéréoscopique dans une configuration de salle de classe. | C16: Université Paris Saclay | D16: Fablab Paris Saclay | E16: http://www.digiscope.fr/fr/platforms/mandelbrot
A17: 15 | B17: MIRE : Grand mur d'image stéréoscopique dans une configuration incurvée. | C17: Université Paris Saclay | D17: Fablab Paris Saclay | E17: http://www.digiscope.fr/fr/platforms/mire
A18: 16 | B18: Sinapse : Powerwall 4K avec affichage 3D et table tactile | C18: Université Paris Saclay | D18: Fablab Paris Saclay | E18: http://www.digiscope.fr/fr/platforms/sinapse
A19: 17 | B19: VIKI : Environment immersif 5 faces, avec tracking et 2 bras haptiques | C19: Université Paris Saclay | D19: Fablab Paris Saclay | E19: http://www.digiscope.fr/fr/platforms/viki
A20: 18 | B20: FABLAB DIGISCOPE | LISN | UPSACLAY : Fablab Digiscope | LISN | UPSaclay est le Laboratoire de Design appliqué à la Fabrication Numérique et le Tiers-Lieux de Université Paris-Saclay. | C20: Université Paris Saclay | D20: Fablab Paris Saclay | E20: http://www.digiscope.fr/fr/platforms/fablab
A21: 19
A22: 20
A23: 21
A24: 22

Sheet Outils
A1: Outils
A2: N | B2: Type | C2: Déscription | D2: Etablissement | E2: Lien | F2: Nom Contact | G2: Mail | H2: Fonction | I2: CONTRIBUTEUR
A3: 1 | B3: Programme Oser pour innover | C3: Site web | D3: PUI | E3: Programme "Oser pour innover" | Université Paris-Saclay | F3: Monica Henao | G3: formation.innovation@universite-paris-saclay.fr | I3: Monica Henao
A4: 2 | B4: Programme Oser pour innover | C4: LinkedIn | D4: PUI | E4: (25) Post | LinkedIn | F4: Monica Henao | G4: formation.innovation@universite-paris-saclay.fr | I4: Monica Henao
A5: 3 | B5: Programme Oser pour innover | C5: INSCRIPTION au programme | D5: PUI | E5: Inscription programme OSER POUR INNOVER | F5: Monica Henao | G5: formation.innovation@universite-paris-saclay.fr | I5: Monica Henao
A6: 4 | B6: Plaquette | C6: L’Université Paris-Saclay, actrice majeure de l’innovation | D6: Univesité Paris Saclay | F6: Cindy AUGUSTO DOS SANTOS | G6: cindy.augusto-dos-santos@universite-paris-saclay.fr | H6: Chargée de communication innovation
A7: 5 | B7: Boîte à outils - Actions Marie Sklodowska-Curie | C7: Kits de montage : tous les documents clefs pour une proposition réussie ! Journées d’information, Formations et ateliers, Conseils pour la rédaction d'une proposition, Tutoriels vidéos - Comment compléter la part A d'une proposition ? | D7: Ministère de l'Enseignement Supérieur | E7: https://www.horizon-europe.gouv.fr/boite-outils-actions-marie-sklodowska-curie-27980 | F7: Eugénia Shadlova | G7: eugenia.shadlova@recherche.gouv.fr | H7: Point de Contact National et Représentante au Comité de Programme Actions Marie Sklodowska-Curie | I7: 33 1 55 55 83 71
A8: 6 | B8: Les innovations de notre quotidien issues de la recherche publique | C8: Jeu| Site créé par le Réseau Curie | D8: Réseau Curie | E8: https://www.mon-quotidien-avec-la-recherche-publique.fr/les-innovations-de-notre-quotidien
A9: 7 | B9: Vidéo innovation 1 LinkedIn | C9: Episode 1: Comprendre l'innovation à l'Université Paris Saclay Le transfert de technologie | D9: Univesité Paris Saclay | E9: https://www.linkedin.com/posts/universit-paris-saclay_comprendre-linnovation-%C3%A0-luniversit%C3%A9-paris-saclay-activity-7259610453931180033-9T_H?utm_source=share&utm_medium=member_desktop
A10: 8 | B10: Vidéo innovation 2 LinkedIn | C10: Episode 2: Comprendre l'innovation à l'Université Paris Saclay la sensibilisation | D10: Univesité Paris Saclay | E10: https://www.linkedin.com/posts/universit-paris-saclay_comprendre-linnovation-%C3%A0-luniversit%C3%A9-paris-saclay-activity-7260584518628052994-l8Fs/?utm_source=share&utm_medium=member_desktop
A11: 9 | B11: Vidéo innovation 3 LinkedIn | C11: Episode 3: Comprendre l'innovation à l'Université Paris Saclay la prématuration et maturation | D11: Univesité Paris Saclay | E11: https://www.linkedin.com/posts/universit-paris-saclay_comprendre-linnovation-%C3%A0-luniversit%C3%A9-paris-saclay-activity-7264289178488606721-VqPD/?utm_source=share&utm_medium=member_desktop
A12: 10 | B12: Vidéo innovation 4 LinkedIn | C12: Episode 4: Comprendre l’innovation : Le prototypage, l’incubation et l’amorçage | D12: Univesité Paris Saclay
A13: 11 | B13: Vidéo innovation 5 LinkedIn | C13: Episode 5: Comprendre l’innovation à l’Université Paris-Saclay : Les dispositifs de collaboration | D13: Univesité Paris Saclay
A14: 12 | B14: Vidéo innovation 1 Youtube | C14: Episode 1: Comprendre l'innovation à l'Université Paris Saclay Le transfert de technologie | D14: Univesité Paris Saclay | E14: Comprendre l'innovation à l'Université Paris-Saclay - Épisode 1 : Le transfert de technologie - YouTube
A15: 13 | B15: Vidéo innovation 2 Youtube | C15: Episode 2: Comprendre l'innovation à l'Université Paris Saclay la sensibilisation | D15: Univesité Paris Saclay | E15: https://www.youtube.com/watch?v=6KD2T42j6Ns
A16: 14 | B16: Vidéo innovation 3 Youtube | C16: Episode 3: Comprendre l'innovation à l'Université Paris Saclay la prématuration et maturation | D16: Univesité Paris Saclay | E16: https://www.youtube.com/watch?v=ZbF2qsJ9ONU
A17: 15 | B17: Vidéo innovation 4 Youtube | C17: Episode 4: Comprendre l’innovation : Le prototypage, l’incubation et l’amorçage | D17: Univesité Paris Saclay | E17: Comprendre l’innovation - Épisode 4 : Le prototypage, l’incubation et l’amorçage
A18: 16 | B18: Vidéo innovation 5 Youtube | C18: Episode 5: Comprendre l’innovation à l’Université Paris-Saclay : Les dispositifs de collaboration | D18: Univesité Paris Saclay | E18: Comprendre l’innovation à l’Université Paris-Saclay - Épisode 5 : Les dispositifs de collaboration
A19: 17 | B19: Office de Tourisme Paris-Saclay | C19: Vidéo de présentation région Paris Saclay | D19: Office de Tourisme Paris-Saclay | E19: https://www.youtube.com/watch?v=OXPz2YYy8Gw&t=1s
A20: 18 | B20: université Paris Saclay Design Spot | C20: Plaquette du Design Spot | D20: Univesité Paris Saclay | E20: https://www.designspot.fr/ | F20: Yoann Montenot | H20: Directeur
A21: 19 | B21: Valo trois petits points | C21: Organisation | E21: https://valo.troispetitspoints.org/
A22: 20 | B22: Site internet HUB PASREL | C22: « PASREL » est un mot-valise pour PAris-Saclay foRmation rEcherche & hôpitaL pour bâtir des ponts entre tous les acteurs de l’innovation en santé | D22: Univesité Paris Saclay | E22: https://www.pasrel.universite-paris-saclay.fr/ | F22: BAUDOUIN-CORNU Peggy et Laurence HOFFMANN Manager de projet | G22: peggy.baudouin@cea.fr | H22: Service Hospitalier Frédéric Joliot (SHFJ) du CEA et soutenu par le CEA, le CNRS, l’Inserm et l’Université Paris-Saclay.
A23: 21 | B23: Deeptech tour BPI France UPSaclay | C23: Résumé edition 2022 | D23: BPI France | E23: DEEPTECH TOUR 2022 - PARIS SACLAY - Best of
A24: 22 | B24: BD Startups Deeptech | C24: Changer le monde une startup à la fois. PDF de cas réels startups | D24: BPI France | E24: https://cdn-assets.inwink.com/ebd05a9d-17e6-4e7b-ba77-a701597bb189/2e9a5464-312d-4249-81e5-77916ee17bc7?sv=2018-03-28&sr=b&sig=eQK9fPC%2FSKQkglAPOtAoGBxM%2FUTx3p63RgizFeQFR0E%3D&se=9999-12-31T23%3A59%3A59Z&sp=r&rscd=inline%3B%20filename%3D%22BPI%2520BD%2520Deeptech%2520Tour%252021-22%2520Master_Digitale_230901_02-avec%2520compression.pdf%22
A25: 23 | B25: Innovation stratégie site web | C25: Outils pour l'innovation et la stratégie | D25: Pascal Corbel | E25: Innovation-strategie.fr
A26: 24 | B26: Biblothèque numérique FOCUS | C26: FOCUS | E26: https://www.bibliotheques.universite-paris-saclay.fr/
A27: 25 | B27: Hoovers | C27: Une base de données spécialisée en veille économique et intelligence commerciale. Elle fournit des informations détaillées sur les entreprises, les tendances sectorielles et la concurrence. Idéal pour identifier des acteurs clés et analyser le marché cible. | D27: Sophie Dondeyne
A28: 26 | B28: Xerfi | C28: Une plateforme d’analyse stratégique axée sur les données financières et sectorielles. Elle aide à comprendre l’évolution des industries et à évaluer les opportunités de marché grâce à des rapports détaillés. Attention, l'abonnement du Lumen ne couvre pas l'intégralité des études. Si une étude intéresse particulièrement un étudiant et qu'elle n'est pas intégrée dans l'abonnement, il est toujours possible de se rendre à la BNF au service du Prisme pour consultation gratuite. | D28: Sophie Dondeyne
A29: 27 | B29: Statista | C29: Une ressource incontournable pour accéder à des statistiques, graphiques et études de marché sur divers secteurs. Parfait pour obtenir des données chiffrées et des tendances globales. | D29: Sophie Dondeyne | E29: France - Statistics & Facts | Statista
A30: 28 | B30: ScholarVox | C30: Bibliothèque numérique spécialisée qui donne accès à des milliers de livres et ressources académiques dans divers domaines (management, entrepreneuriat, ingénierie, sciences sociales, etc.). Elle permet aux étudiants et chercheurs de consulter des ouvrages en ligne, d’effectuer des recherches ciblées et d’accéder à des analyses récentes. C’est un outil idéal pour approfondir ses connaissances, réaliser une veille stratégique ou structurer un projet entrepreneurial grâce à des références académiques et professionnelles de qualité. | D30: Sophie Dondeyne | E30: Accueil - ScholarVox Université
A31: 29 | B31: Europresse | C31: Une base de données spécialisée dans la presse et l’information économique. Elle donne accès à des milliers d’articles issus de journaux, magazines et sources d’actualités internationales, nationales et régionales. Idéale pour une veille stratégique, elle permet aux étudiants et entrepreneurs de suivre les tendances du marché, d’analyser la concurrence et de s’informer sur les évolutions sectorielles. Grâce à ses outils de recherche avancés, Europresse facilite l’accès à des sources fiables et variées pour alimenter une étude de marché ou un projet entrepreneurial. | D31: Sophie Dondeyne | E31: Accueil - Europresse
A32: 30 | B32: Ressources numériques LUMEN | C32: Accompagnement personnalisé pour réaliser des études de marché et des ressources numériques, responsable des services aux publics au Lumen. | D32: Imelda Lemoing | E32: Lumen | G32: imelda.lemoing@universite-paris-saclay.fr
A33: 31 | B33: Research Connect | C33: Avant Open4research utile pour la recherche de fonds partout dans le monde. Discover a range of funding opportunities available for universities and research institutions across the world. | E33: https://www.myresearchconnect.com/
A34: 32 | B34: Catalogue de formations Innovation pédagogique "AIRTABLE" | C34: Nombreuses formations sur l'innovation pédagogique proposées par la Direction de l'Innovation pédagogique UPSaclay | D34: Hugues Cazin | E34: Airtable - Gallery | G34: hugues.cazin@universite-paris-saclay.fr | H34: Responsable pôle ressources et dispositifs pédagogiques
A35: 33 | B35: Cartographie des lieux de l'innovation du territoire | C35: Cartographie des lieux d’innovation et des start-up de Paris-Saclay | D35: EPAPS | E35: http://paris-saclay-startup.com/map/index.html#/ | F35: Frédéric Devaivre | G35: frederic.devaivre@oin-paris-saclay.fr
A36: 34 | B36: Pépite escape game | C36: Développer l'esprit d'entrerendre avec Pépite et région pays de la Loire | D36: PEPITE | E36: https://www.pepite-pdl.fr/escape-game/
A37: 35 | B37: Observatoire des territoires | E37: Page d'accueil | L'Observatoire des Territoires
A38: 36 | B38: Annuaire des pôles de compétitivité | C38: Ministere de l'Economie | D38: Gouvernement | E38: Annuaire des pôles de compétitivité - Page 6 sur 6 - Direction générale des Entreprises | Direction générale des Entreprises
A39: 37 | B39: ScanR | C39: Explorer le monde de la Recherche et de l'Innovation françaises avec scanR | D39: Gouvernement | E39: https://scanr.enseignementsup-recherche.gouv.fr/
A40: 38 | B40: Science Ouverte | C40: Baromètre français de la Science Ouverte | D40: Gouvernement | E40: https://barometredelascienceouverte.esr.gouv.fr/
A41: 39 | B41: CurieXplore | C41: La plateforme d'exploration des systèmes d'enseignement supérieur, de recherche et d'innovation à l'international | D41: Gouvernement | E41: https://curiexplore.enseignementsup-recherche.gouv.fr/
A42: 40 | B42: dataESR | C42: #dataESR vous aide à trouver les ressources en données sur l'enseignement supérieur, la recherche et l'innovation | D42: Gouvernement | E42: https://data.esr.gouv.fr/FR/
A43: 41 | B43: RNSR | C43: Répertoire national des structures de recherche - RNSR | D43: Gouvernement | E43: https://data.enseignementsup-recherche.gouv.fr/explore/dataset/fr-esr-repertoire-national-structures-recherche/information/
A44: 42 | B44: I LAB | C44: Lauréats I-LAB Concours national d'aide à la création d'entreprises de technologies innovantes | D44: Gouvernement | E44: https://data.enseignementsup-recherche.gouv.fr/explore/dataset/fr-esr-laureats-concours-national-i-lab/table/
A45: 43 | B45: Design spot | C45: Revivre les évènements du Design Spot | D45: Yoann Montenot | E45: https://www.designspot.fr/evenements
A46: 44 | B46: Podcast Innovation | C46: Podcast les typologies de l'innovation | D46: Pascal Corbel | E46: https://www.podcastics.com/podcast/episode/les-typologies-dinnovation-367170/
A47: 45 | B47: Inncyclopédie | C47: Comprendre l'innovation sous toutes ses formes | E47: https://inncyclopedie.fr/
A48: 46 | B48: Portraits de chercheurs et chercheuses | C48: Publication et valorisation de chercheurs et chercheuses | D48: Véronique Meder | E48: https://www.universite-paris-saclay.fr/recherche/portraits-de-chercheurs-et-de-chercheuses
A49: 47 | B49: Appels à projets recherche valorisation Université Paris Saclay | C49: Différentes sources de financement pour les porteurs au périmètre large de l'Université Paris-Saclay | D49: admin.direv@universite-paris-saclay.fr | E49: https://www.universite-paris-saclay.fr/recherche/appel-projets-recherche-et-valorisation
A50: 48 | B50: Bibliolabs | C50: BiblioLabs est une application permettant d'agréger, de comparer et d'analyser les données bibliographiques et bibliométriques concernant la littérature scientifique et académique des structures de recherche de l'Université Paris-Saclay. | D50: DIBISO | E50: Accueil - BiblioLabs
A51: 49 | B51: ORCID | C51: ORCID is a free, unique, persistent identifier (PID) for individuals to use as they engage in research, scholarship, and innovation activities. | E51: ORCID
A52: 50 | B52: HAL | C52: L’archive ouverte HAL est un réservoir de documents scientifiques, publiés ou non, produits dans le contexte de recherche scientifique et d’enseignement supérieur. | E52: HAL - Université Paris-Saclay | Université Paris-Saclay
A53: 51 | B53: Design spot | C53: 12/11/25 au 13/03/26 France design Impact Award : 40 projets de design pour transformer le monde | D53: Yoann Montenot | E53: France Design Impact Award | F53: Yoann Montenot | G53: yoann.montenot@universite-paris-saclay.fr
A54: 52 | B54: Portraits de chercheurs et de chercheuses | C54: Présente les portrais de chercheurs et chercheuses de l'université Paris-Saclay et de son écosystème | D54: Véronique Meder | E54: https://www.universite-paris-saclay.fr/recherche/portraits-de-chercheurs-et-de-chercheuses
A55: 53 | B55: Design spot Exposition | C55: 9/02 au 12/04/26 L’énergie du Vivant. Raconter la bio-inspiration : de la recherche au grand public. Quand les stratégies du vivant éclairent les solutions de demain | D55: Yoann Montenot | E55: https://www.designspot.fr/evenements/lenergie-du-vivant | F55: Yoann Montenot | G55: yoann.montenot@universite-paris-saclay.fr
A56: 54 | B56: Design spot Exposition | C56: Événement de clôture | D56: 46114 | F56: Yoann Montenot | G56: yoann.montenot@universite-paris-saclay.fr
A57: 55 | B57: Design spot Exposition | C57: Table ronde | F57: Yoann Montenot | G57: yoann.montenot@universite-paris-saclay.fr
A58: 56 | B58: Maison des Sciences sociales et des Humanités Paris-Saclay | C58: Créée le 1er janvier 2015, (UAR3683) est une unité d’appui et de recherche dédiée à l’avancement des sciences humaines et sociales. Située au cœur du plateau de Saclay, elle a pour objectif de développer l’innovation, le dialogue et la collaboration entre chercheurs de diverses disciplines scientifiques. | E58: https://msh-paris-saclay.fr/ | F58: Formulaire de contact | G58: https://msh-paris-saclay.fr/contact/
A59: 57 | B59: Office quebéquois de la langue française | C59: Portail permettant la traduction de termes scientifiques du fraçais à l'anglais | D59: Québec | E59: agroalimentaire | GDT | F59: Monica Henao | G59: formation.innovation@universite-paris-saclay.fr
A60: 58 | B60: De la recherche à la startup | C60: Video témoignage de Bernard Yannou, Directeur adjoint de la recherche Centrale Supelec, en charge de l'innovation | D60: IPSA | E60: PlayPlay | F60: Bernard Yannou | G60: bernard.yannou@centralesupelec.fr
A61: 59 | B61: Academia.edu met en réseau les chercheurs | C61: Amplify your research. Publish and disseminate your work, track your impact, and discover new research. | D61: ACADEMIA.EDU | E61: https://www.academia.edu/ | F61: Monica Henao | G61: formation.innovation@universite-paris-saclay.fr
A62: 60 | B62: ARISTOTE IA | C62: Aristote, une IA au service de l'enseignement supérieur | D62: Centrale Supelec | E62: Aristote, une IA au service de l'enseignement supérieur | CentraleSupélec | F62: Bernard Yannou | G62: bernard.yannou@centralesupelec.fr
A63: 61 | B63: Podcast CNRS | C63: Podacast sur le fil de l'innovation | D63: CNRS | E63: Podcast | Sur le fil de l'innovation | CNRS | F63: David Néron
A64: 62 | B64: Choisir sa formation Université Paris Saclay | C64: Plateforme du premier cycle au doctorat, en passant par des programmes de grandes écoles, l’Université Paris-Saclay déploie une offre de formation sur un large spectre de disciplines, au service de la réussite étudiante et de l'insertion professionnelle. | D64: Univesité Paris Saclay | E64: Choisir sa formation | Université Paris-Saclay | F64: Sylvie Cyprien | G64: relations.entreprises@universite-paris-saclay.fr
A65: 63
A66: 64
A67: 65

Sheet Bibliographie
A1: Bibliographie
A2: N | B2: Titre | C2: Auteur | D2: Année | E2: Type | F2: Lien de référence | G2: ISBN | H2: Notes | I2: Localisation | J2: CONTRIBUTEUR
A3: 1 | B3: Qu'est ce que l'innovation? | C3: Joanna de Bruijn | D3: 2015 | F3: https://fr.slideshare.net/slideshow/global-innovation-43184763/43184763#22
A4: 2 | B4: Les nouveaux entrepreneurs du public : de la recherche académique à la création d'entreprises | C4: Raffini, Daphnée (Auteur) ; Tourin, Arnaud, (Auteur) ; Fink, Mathias | D4: 2023 | E4: Livre | F4: https://upsaclay.focus.universite-paris-saclay.fr/primo-explore/fulldisplay?docid=33PUP_Alma_UNIMARC21274524540006051&context=L&vid=33UDPS_VU1&lang=fr_FR&search_scope=default_scope&adaptor=Local%20Search%20Engine&tab=default_tab&query=any,contains,le%20nouveaux%20entrepreneurs%20du%20public&offset=0 | I4: BU Orsay
A5: 3 | B5: La ludopédagogie, acteurs et idéologie | C5: Michel Lavigne | D5: 2022 | E5: Revue : Educations | F5: https://www.openscience.fr/La-ludopedagogie-acteurs-et-ideologie | I5: BU Orsay
A6: 4 | B6: Recherche, formation, innovation : quel rôle pour les Grandes Ecoles ? | C6: Levy Jacques | D6: 1988 | E6: Conférence | F6: https://upsaclay.focus.universite-paris-saclay.fr/primo-explore/fulldisplay?docid=33PUP_Alma_UNIMARC21141108180006051&context=L&vid=33UDPS_VU1&lang=fr_FR&search_scope=default_scope&adaptor=Local%20Search%20Engine&tab=default_tab&query=any,contains,formation%20innovation&offset=0 | I6: BU Orsay
A7: 5 | B7: Former Avec Le Funny Learning : De La Formation à La Facilitation : Transformez Votre PéDagogie | C7: Boussuat, Brigitte., and Jean Lefèbvre | D7: 2020 | E7: Print. Hors Collection | I7: BU Orsay
A8: 6 | B8: Management Interculturel. Comprendre et gérer la diversité culturelle | C8: Ulrike Mayrhofer | D8: 2017 | E8: Livre | F8: Lumen 658,4 | H8: 10 études de cas réels | I8: LUMEN
A9: 7 | B9: Coopération internationale en R&D : les effets de la distance sur le choix de pays partenaires | C9: Angué K et Mayrhofer U | D9: 2010 | E9: Revue | F9: référence de N, 6 | I9: ND
A10: 8 | B10: Management interculturel et styles d'apprentissage | C10: Barmeyer C Meier O | D10: 2006 | E10: Presses de l'Université de Laval | F10: Ref N 6 | I10: ND
A11: 9 | B11: Recherche, développement & innovation - Témoignages et stratégies pour catalyser croissance et industrialisation | C11: ANRT et Onepoint | D11: 2024 | E11: Livre | F11: Ouvrage_R&DI_Onepoint_ANRT_2024.pdf
A12: 10 | B12: La répétition espacée : Comment se souvenir de tout | C12: Nicky Case | D12: 2018 | E12: Outil numérique | F12: https://ncase.me/remember/fr.html | H12: Outil intéractif sur la mémoire et apprentissage | I12: ND
A13: 11 | B13: Mieux apprendre et étudier : les (vraies) techniques scientifiques | C13: David Louapre | D13: 2023 | E13: Vidéo | F13: https://www.youtube.com/watch?v=RVB3PBPxMWg | I13: ND
A14: 12 | B14: La méthode des cartes mentales | C14: David Louapre | D14: 2023 | E14: Vidéo | F14: https://scienceetonnante.com/2023/09/15/la-methode-des-cartes-mentales/ | H14: Blog avec vidéo | I14: ND
A15: 13 | B15: Que sais-je : Le Design | C15: Stéphane Vial | D15: 2015 | E15: Livre | F15: https://www.quesaisje.com/accueil | G15: 978-2-13-062043-3 | I15: LUMEN
A16: 14 | B16: Trouver des informations pour faire son étude de marché | C16: BPI France | D16: 2023 | E16: Site web | F16: https://bpifrance-creation.fr/encyclopedie/letude-marche/comment-faire-son-etude-marche/trouver-informations-faire-son-etude | H16: Pass créa de BPI France | I16: Web
A17: 15 | B17: Intrapreneuriat Innovation et croissance | C17: Véronique Bouchard | D17: 2009 | E17: Livre | G17: 978-2-10-052238-5 | I17: LUMEN
A18: 16 | B18: Ces créateurs d'entreprises innovantes. Quand doctorat se conjugue avec entrepreneuriat | C18: Clarisse Angelier, Jeanne Courouble | D18: 2012 | E18: Livre | G18: 978-2-212-55271-3 | I18: LUMEN
A19: 17 | B19: Les 100 mots de l'éducation | C19: Patrick Rayou, Agnès van Zanten | D19: 2011 | E19: Livre | G19: 978-2-13-058260-1 | I19: LUMEN
A20: 18 | B20: Gestion de l'innovation: comprendre le processus de l'innovation pour le piloter | C20: Thomas Loilier, Albéric Tellier | D20: 2013 | E20: Livre | G20: 978-2-84769-508-3 | I20: BU Orsay
A21: 19 | B21: Le marketing de l'innovation. Concevoir et lancer de nouveaux produits et services 4è Edition | C21: Linda Hamdi-Kidar, Aurélie Hemonnet, Emmanuelle Le Nagard, Delphine Manceau, Sophie Morin-Delerm | D21: 2022 | E21: Livre | G21: 978-2-10-084092-2 | I21: BU Orsay
A22: 20 | B22: Perspective en education et formation. Approche didactique de l'interdisciplinarité | C22: Alain Maingais, Barbara Dufour, Gérard Fourez | D22: 2002 | E22: Livre | G22: 2-8041-3839-9 | I22: BU Orsay
A23: 21 | B23: Management de l'innovation 2è Edition | C23: Richard Soparnot, Eric Stevens | D23: 2007 | E23: Livre | G23: 978-2-10-051079-5 | I23: BU Orsay
A24: 22 | B24: 100 idées pour faire classe autrement ou comment les pédagogies coopératives changent la vie de l'école | C24: Christophe Charpiot, Fahima Melizi, Cédric Gueyraud | D24: 2020 | E24: Livre | G24: 978-2-35-345-221-7 | I24: BU Orsay
A25: 23 | B25: L'innovation pédagogique. de la théorie à la pratique | C25: Isabelle Capron Puozzo, Aleksandra Vuichard | D25: 2022 | E25: Livre | G25: 978-2-88930-477-6 | I25: BU Orsay
A26: 24 | B26: Management de l'innovation. Enjeux principes et méthodes | C26: Claudine Gay, Bérangère L. Szostak | D26: 2022 | E26: Livre | G26: 978-2-10-083708-3 | I26: BU Orsay
A27: 25 | B27: La jungle de l'innovation Comment survivre et prospérer | C27: Rémy Maniak, Nicolas Mottis | D27: 2021 | E27: Livre | G27: 978-2-10-081321-6 | I27: Collection personnelle
A28: 26 | B28: Créativité et innovation. Intelligence collective au service du management de projets | C28: Tayeb Louafa, Francis-Luc Perret | D28: 2008 | E28: Livre | G28: 978-2-88074-721-3 | I28: BU Orsay
... A31: 29 | B31: La boite à outils pour animer vos réunions | C31: Florence Gillet, Laurent Maimi | D31: 2020 | E31: Livre | G31: 978-2-10-080797-0 | I31: LUMEN
A32: 30 | B32: L'innovation pour les nuls | C32: Jerôme Lafont
A33: 31 | B33: The innovators solution | C33: Clayton M Christensen, Michael E. Raynor | D33: 2003 | E33: Livre | G33: 978-1-57851-852-4 | I33: LUMEN
A34: 32 | B34: 8 Priorités pour dynamiser l'innovation en France | C34: Think Tank Innovation Association des Centraliens | D34: 2011 | E34: Livre | G34: 978-2-200-27667-6 | I34: LUMEN

Sheet Feuil1
B2: https://clickup.com/lp?utm_source=google&utm_medium=cpc&utm_campaign=gs_cpc_arlv_nnc_brand_trial_all-devices_troas_lp_x_all-departments_x_brand&utm_content=all-countries_kw-target_text_all-industries_all-features_all-use-cases_clickup_broad&utm_term=b_clickup&utm_creative=651395805263_BrandChampion-03072023_rsa&utm_custom1=&utm_custom2=&gad_source=1&gclid=Cj0KCQjwpP63BhDYARIsAOQkATa2ufLqJBfBfD-FpNgMNi54nLgeRAt9WAUfKaUWj57IrA8MY3n3RAEaAunNEALw_wcB
B3: https://www.openscience.fr/La-ludopedagogie-acteurs-et-ideologie
B4: https://dz03nossv7tsm.cloudfront.net/media/filer_public/36/3d/363dfbd3-016f-4eb8-b63b-fdb0f7f66583/syllabus_ef001.pdf
B5: https://www.fun-mooc.fr/fr/cours/enseigner-avec-le-jeu/
B6: https://www.ac-and-o.com/formation/creer-un-outil-de-suivi-du-plan-de-formation/
B7: https://www.google.com/search?q=spirale+de+innovation&sca_esv=433eaf814a238d09&rlz=1C1CHBD_frFR1035FR1035&udm=2&biw=1920&bih=919&sxsrf=ADLYWIL4Oxuzx8kKYle8Q6_-r-cbfAj3yw%3A1727939924480&ei=VEX-Zu6DHZSKkdUPtKX7kAE&ved=0ahUKEwju_ZDr1fGIAxUURaQEHbTSHhIQ4dUDCBA&oq=spirale+de+innovation&gs_lp=Egxnd3Mtd2l6LXNlcnAiFXNwaXJhbGUgZGUgaW5ub3ZhdGlvbkjbIFCmBVikE3ABeACQAQCYAS-gAY0DqgECMTC4AQzIAQD4AQGYAgOgAlXCAgoQABiABBhDGIoFwgIFEAAYgATCAgYQABgIGB7CAgcQABiABBgYmAMAiAYBkgcBM6AHqAc&sclient=gws-wiz-serp#vhid=uEAnaoArUh5MHM&vssid=mosaic
B8: https://ens-paris-saclay.fr/bibliotheque/ressources-documentaires

Sheet Financements
B1: Niveau | C1: Organisme / Appel à projets | D1: Lien direct vers l’appel / dispositif
A2: 1 | B2: Local | C2: Université Paris-Saclay | D2: https://www.universite-paris-saclay.fr/recherche/appel-projets-recherche-et-valorisation
A3: 2 | C3: SATT PARIS SACLAY | D3: La SATT Paris Saclay œuvre pour les chercheurs
A4: 3 | C4: IncubAlliance | D4: https://www.incuballiance.fr/programmes-accompagnement
A5: 4 | B5: Île-de-France (régional / local) | C5: Région Île-de-France – Aides et appels à projets (toutes aides incluses) | D5: https://www.iledefrance.fr/aides-et-appels-a-projets
A6: 5 | C6: Région Île-de-France – Grands projets de recherche / RDI (FEDER) | D6: https://www.europeidf.fr/jai-un-projet/appels-a-projets/grands-projets-de-recherche-developpement-et-innovation-lies-aux
A7: 6 | C7: DIMs et programmes de financement thématiques (ex. DIM ELICIT) | D7: https://dim-elicit.fr/en/calls-for-projects/
A8: 7 | C8: Programme Paris Region PhD – allocations doctorales | D8: https://www.iledefrance.fr/aides-et-appels-a-projets/paris-region-phd-2025
A9: 8 | B9: France | C9: ANR – Agence nationale de la recherche (appels en cours & à venir) | D9: https://anr.fr/fr/france-2030/appels/
A10: 9 | C10: ANR | D10: https://anr.fr/fr/detail/call/aapg-appel-a-projets-generique-2026/
A11: 10 | C11: BPI France | D11: https://www.bpifrance.fr/nos-appels-a-projets-concours
A12: 11 | C12: ANRT CIFRE | D12: https://offres-et-candidatures-cifre.anrt.asso.fr/
A13: 12 | C13: Institut Universitaire de France | D13: https://www.iufrance.fr/liuf-vous-donne-droit-a.html
A14: 13 | C14: Portail Europe en France – appels à projets cofinancés | D14: Trouver une aide pour financer son projet | L'Europe s'engage en France, le portail des Fonds européens
A15: 14 | C15: Veille multi-sources sur les appels en France. | D15: https://www.appelsprojetsrecherche.fr/
A16: 15 | B16: Europe (UE) | C16: Programme Horizon Europe – financement R&I (principal cadre) | D16: Homepage - Research and innovation - European Commission
A17: 16 | C17: Portail des appels européens (fonds et programmes) | D17: Funding opportunities - Research and innovation - European Commission
A18: 17 | C18: Marie Skłodowska-Curie Actions (bourses mobilité & recherche) | D18: Funding - Marie Skłodowska-Curie Actions
A19: 18 | C19: European Research Council (ERC) – subventions de pointe | D19: Apply for an ERC Grant – Secure Funding for Frontier Research
A20: 19 | C20: ERASMUS + | D20: Accueil - Erasmus+
A21: 20 | B21: International | C21: Grant GOV -United States government | D21: https://simpler.grants.gov/search?utm_source=Grants.gov
A22: 21 | C22: NIH (National Institutes of Health, USA) – financements internationaux | D22: https://grants.nih.gov/

Sheet Se former avenir
B1: Se former pour l'avenir
A2: 1 | B2: Action 1 | C2: Calendrier Formation Entrepreneuriat Deeptech | D2: Roberta Camera | E2: https://adum.fr/script/catalogue.pl?site=psaclay&cat=PSaclayEntrepre | F2: Programme annuel
A3: 2 | B3: Action 2 | C3: Programme Oser pour innover | D3: Christophe Dubois, Christelle Hanoun, Rita Noelle Moussa, Monica Henao | E3: Inscription programme OSER POUR INNOVER – Fill out form | F3: Programme annuel
A4: 3 | B4: Action 3 | C4: Programme formation manager entreprise | D4: Jeannie Bisson | E4: IFA | F4: Sur appel à candidatures
A5: 4 | B5: Institut de formation des personnels et observatoire de compétences | C5: Programme de formations de l'Institut | D5: IFPOC | E5: https://geforp.esup-portail.org/program/myprogram | F5: Programme annuel
A6: 5 | B6: Formation intelligence Artificielle | C6: Brevet AI | D6: DATAIA | E6: inscription-brevetai@ens-paris-saclay.fr
A7: 6 | B7: Développement soutenable | C7: Demain autrement

Sheet Etablissements Valo
A1: Etablissements
B2: Etablissement | C2: Site web | D2: Contact Cellule Valo
A3: 1 | B3: AgroParisTech | C3: AgroParisTech
A4: 2 | B4: Centrale Supélec | C4: Centrale Supélec
A5: 3 | B5: ENS Paris-Saclay | C5: ENS Paris-Saclay
A6: 4 | B6: CNRS | C6: CNRS
A7: 5 | B7: INRAE | C7: INRAE
A8: 6 | B8: INRIA | C8: Inria
A9: 7 | B9: INSERM | C9: https://www.inserm.fr/
A10: 8 | B10: Institut d'Optique Graduate School | C10: IOGS
A11: 9 | B11: Université d'Evry Paris-Saclay | C11: Université d'Évry
A12: 10 | B12: Université Paris-Saclay | C12: Université Paris-Saclay
A13: 11 | B13: Université Versailles Saint-Quentin en Yvelines | C13: Université de Versailles Saint-Quentin-en-Yvelines | D13: valorisation@uvsq.fr
A14: 12 | B14: SATT PARIS SACLAY | C14: https://satt-paris-saclay.fr/
A15: 13 | B15: IncubAlliance Paris-Saclay | C15: https://www.incuballiance.fr/
C16: CEA
C17: Onera
B18: IHES | C18: IHES
